src/controllers/inst_controller.v
// ===========================================
// Instruction Memory Controller Module
// 
// Memory controller to handle requests from the fetcher 
// of the different compute units
// ===========================================
module inst_controller #(
  parameter NUM_MEM_CHAN = 1,
            NUM_CORES = 4,
            MEM_ADDR_WIDTH = 8,
            MEM_DATA_WIDTH = 16
) (
  input clk,
  input reset,

  // I/O from internal GPU Fetcher blocks 
  output fetch_req_rdy [NUM_CORES-1:0], 
  input fetch_req_val [NUM_CORES-1:0], 
  input [MEM_ADDR_WIDTH-1:0] fetch_req_addr [NUM_CORES-1:0],

  input fetch_resp_rdy [NUM_CORES-1:0], 
  output fetch_resp_val [NUM_CORES-1:0],
  output [MEM_DATA_WIDTH-1:0] fetch_resp_inst [NUM_CORES-1:0],

  // I/O to interface with global memory
  input mem2fetch_req_rdy,
  output mem2fetch_req_val,
  output [MEM_ADDR_WIDTH-1:0] mem2fetch_req_addr, // Uses current pc

  output mem2fetch_resp_rdy, 
  input mem2fetch_resp_val,
  input [MEM_DATA_WIDTH-1:0] mem2fetch_resp_inst,

  // For debugging
  output [NUM_CORES-1:0] compute_unit
);

// Progression localparam
localparam  IDLE = 2'd0,      // Channel is waiting for a memory request
            REQUEST = 2'd1,   // Channel is processing the mem req
            RESPONSE = 2'd2;  // Channel is sending mem resp to appropriate compute unit

reg [1:0] channel_state;
reg [NUM_CORES-1:0] selected_unit;
assign compute_unit = selected_unit;


// Registering outputs 
reg fetch_req_rdy_reg [NUM_CORES-1:0];
reg fetch_resp_val_reg [NUM_CORES-1:0];
reg [MEM_DATA_WIDTH-1:0] fetch_resp_inst_reg [NUM_CORES-1:0];
reg mem2fetch_req_val_reg;
reg [MEM_ADDR_WIDTH-1:0] mem2fetch_req_addr_reg;
reg mem2fetch_resp_rdy_reg;

genvar k;
for (k=0;k<NUM_CORES;k=k+1) begin 
  // assign fetch_req_rdy[i] = fetch_req_rdy_reg[i];
  assign fetch_req_rdy[k] = mem2fetch_req_rdy;
  assign fetch_resp_val[k] = fetch_resp_val_reg[k];
  assign fetch_resp_inst[k] = fetch_resp_inst_reg[k];
end

// integer j;
// for (j=0;j<NUM_MEM_CHAN;j=j+1)begin 
//   assign fetch_req_val[j] = fetch_req_val_reg[j];
//   assign fetch_req_addr_reg[j] = fetch_req_addr_reg[j];
//   assign fetch_resp_rdy_reg[j] = fetch_resp_rdy_reg[j];
// end

assign mem2fetch_req_val = mem2fetch_req_val_reg;
assign mem2fetch_req_addr = mem2fetch_req_addr_reg;
assign mem2fetch_resp_rdy = mem2fetch_resp_rdy_reg;

integer i;
always @(posedge clk) begin 
  if (reset) begin 
    for (i=0;i<NUM_CORES;i=i+1) begin 
      // fetch_req_rdy_reg[i] <= 0;
      fetch_resp_val_reg[i] <= 0;
      fetch_resp_inst_reg[i] <= 0;
    end
    // for (j=0;j<NUM_MEM_CHAN;j=j+1)begin 
    //   fetch_req_val[j] <= 0;
    //   fetch_req_addr_reg[j] <= 0;
    //   fetch_resp_rdy_reg[j] <= 0;
    //   channel_state[j] <= 0;
    // end
    mem2fetch_req_val_reg <= 0;
    mem2fetch_req_addr_reg <= 0;
    mem2fetch_resp_rdy_reg <= 0;
    channel_state <= IDLE;
    selected_unit <= 0;
  end else begin 
    case (channel_state)
  
      IDLE: begin 
        // Loop through all of our cu to find a fetcher that is ready
        for (i=0;i<NUM_CORES;i=i+1)begin 
          if (fetch_req_val[i]) begin 
            // Identified that cu[i] is ready 
            selected_unit <= i;
            // Selecting cu[i]'s signals to pass onto the output
            mem2fetch_req_addr_reg <= fetch_req_addr[i];
            mem2fetch_req_val_reg <= fetch_req_val[i];
            mem2fetch_resp_rdy_reg <= 1; // Ready to accept response
            channel_state <= REQUEST;
            i = NUM_CORES-1; // Synthesizable logic to quit the loop
          end
        end
      end
      REQUEST: begin 
        // Wait until we hear back from the memory 
        if (mem2fetch_resp_rdy) begin 
          fetch_resp_inst_reg[selected_unit] <= mem2fetch_resp_inst;
          fetch_resp_val_reg[selected_unit] <= mem2fetch_resp_val;
          mem2fetch_resp_rdy_reg <= 0; // Disable the signal 
          channel_state <= RESPONSE;
        end 
      end
      RESPONSE: begin
        // Wait until we hear back from the core 
        // THOUGHT: I think because it only requires 1 cycle in fetcher
        // we can simply move back to IDLE and reset values
        channel_state <= IDLE;
        // "unlink" the wiring
        fetch_resp_inst_reg[selected_unit] <= 0;
        fetch_resp_val_reg[selected_unit] <= 0; 
      end

    endcase
  end
end

// For dumping 


endmodule

wrapper/controller/wrapper_instcont.v
`include "../../src/controllers/inst_controller.v"
module wrapper_instcont #(
  parameter NUM_MEM_CHAN = 1,
            NUM_CORES = 4,
            MEM_ADDR_WIDTH = 8,
            MEM_DATA_WIDTH = 16
) (
  input clk,
  input reset,

  // I/O from internal GPU Fetcher blocks 
  output fetch_req_rdy [NUM_CORES-1:0], 
  input fetch_req_val [NUM_CORES-1:0], 
  input [MEM_ADDR_WIDTH-1:0] fetch_req_addr [NUM_CORES-1:0],

  input fetch_resp_rdy [NUM_CORES-1:0], 
  output fetch_resp_val [NUM_CORES-1:0],
  output [MEM_DATA_WIDTH-1:0] fetch_resp_inst [NUM_CORES-1:0],

  // I/O to interface with global memory
  input mem2fetch_req_rdy,
  output mem2fetch_req_val,
  output [MEM_ADDR_WIDTH-1:0] mem2fetch_req_addr, // Uses current pc

  output mem2fetch_resp_rdy, 
  input mem2fetch_resp_val,
  input [MEM_DATA_WIDTH-1:0] mem2fetch_resp_inst,

  output [NUM_CORES-1:0] compute_unit
);

inst_controller #(
  .NUM_MEM_CHAN(NUM_MEM_CHAN),
  .NUM_CORES(NUM_CORES),
  .MEM_ADDR_WIDTH(MEM_ADDR_WIDTH),
  .MEM_DATA_WIDTH(MEM_DATA_WIDTH)
) instructions (
  .clk(clk),
  .reset(reset),
  .fetch_req_rdy(fetch_req_rdy),
  .fetch_req_val(fetch_req_val),
  .fetch_req_addr(fetch_req_addr),
  .fetch_resp_rdy(fetch_resp_rdy),
  .fetch_resp_val(fetch_resp_val),
  .fetch_resp_inst(fetch_resp_inst),
  .mem2fetch_req_rdy(mem2fetch_req_rdy),
  .mem2fetch_req_val(mem2fetch_req_val),
  .mem2fetch_req_addr(mem2fetch_req_addr),
  .mem2fetch_resp_rdy(mem2fetch_resp_rdy),
  .mem2fetch_resp_val(mem2fetch_resp_val),
  .mem2fetch_resp_inst(mem2fetch_resp_inst),
  .compute_unit(compute_unit)
);

// Dumping
initial begin 
  $dumpfile("instcont_dump.vcd");
  $dumpvars(0, instructions);
end

endmodule

test/controller_test/instcont_dump.vcd
$date
	Sun Jan 12 13:16:12 2025
$end
$version
	Icarus Verilog
$end
$timescale
	1ps
$end
$scope module wrapper_instcont $end
$scope module instructions $end
$var wire 1 ! clk $end
$var wire 4 " compute_unit [3:0] $end
$var wire 8 # mem2fetch_req_addr [7:0] $end
$var wire 1 $ mem2fetch_req_rdy $end
$var wire 1 % mem2fetch_req_val $end
$var wire 16 & mem2fetch_resp_inst [15:0] $end
$var wire 1 ' mem2fetch_resp_rdy $end
$var wire 1 ( mem2fetch_resp_val $end
$var wire 1 ) reset $end
$var parameter 2 * IDLE $end
$var parameter 32 + MEM_ADDR_WIDTH $end
$var parameter 32 , MEM_DATA_WIDTH $end
$var parameter 32 - NUM_CORES $end
$var parameter 32 . NUM_MEM_CHAN $end
$var parameter 2 / REQUEST $end
$var parameter 2 0 RESPONSE $end
$var reg 2 1 channel_state [1:0] $end
$var reg 8 2 mem2fetch_req_addr_reg [7:0] $end
$var reg 1 3 mem2fetch_req_val_reg $end
$var reg 1 4 mem2fetch_resp_rdy_reg $end
$var reg 4 5 selected_unit [3:0] $end
$var integer 32 6 i [31:0] $end
$scope begin genblk1[0] $end
$var parameter 2 7 k $end
$upscope $end
$scope begin genblk1[1] $end
$var parameter 2 8 k $end
$upscope $end
$scope begin genblk1[2] $end
$var parameter 3 9 k $end
$upscope $end
$scope begin genblk1[3] $end
$var parameter 3 : k $end
$upscope $end
$upscope $end
$upscope $end
$enddefinitions $end
$comment Show the parameter values. $end
$dumpall
b11 :
b10 9
b1 8
b0 7
b10 0
b1 /
b1 .
b100 -
b10000 ,
b1000 +
b0 *
$end
#0
$dumpvars
bx 6
bx 5
x4
x3
bx 2
bx 1
0)
z(
x'
bz &
x%
z$
bx #
bx "
1!
$end
#500
0!
#1000
b0 "
b0 5
b0 1
0'
04
b0 #
b0 2
0%
03
b100 6
1!
1)
#1500
0!
#2000
b100 6
1!
0)
#2500
0!
#3000
b100 6
1!
#3500
0!
#4000
b100 6
1!
#4500
0!
#5000
b100 6
1!
#5500
0!
#6000
b100 6
1!
#6500
0!
#7000
b100 6
1!
#7500
0!
#8000
b100 6
1!
#8500
0!
#9000
b100 6
1!
#9500
0!
#10000
b100 6
1!
b0 &
0(
1$
#10500
0!
#11000
b1 1
1'
14
1%
13
b110 #
b110 2
b100 6
1!
#11500
0!
#12000
b1001000000101001 &
1(
0$
b10 1
0'
04
1!
#12500
0!
#13000
b0 &
0(
1$
b0 1
1!
#13500
0!
#14000
0$
b1 1
1'
14
b100 6
1!
#14500
0!
#15000
b1001000000101001 &
1(
b10 1
0'
04
1!
#15500
0!
#16000
b0 &
0(
1$
b0 1
1!
#16500
0!
#17000
0$
b1 1
1'
14
b100 6
1!
#17500
0!
#18000
b1001000000101001 &
1(
b10 1
0'
04
1!
#18500
0!
#19000
b0 &
0(
1$
b0 1
1!
#19500
0!
#20000
0$
b1 1
1'
14
b100 6
1!
#20500
0!
#21000
b1001000000101001 &
1(
b10 1
0'
04
1!
#21500
0!
#22000
b0 &
0(
1$
b0 1
1!
#22500
0!
#23000
0$
b1 1
1'
14
b100 6
1!
#23500
0!
#24000
b1001000000101001 &
1(
b10 1
0'
04
1!
#24500
0!
#25000
b0 &
0(
1$
b0 1
1!
#25500
0!
#26000
0$
b1 1
1'
14
b100 6
1!
#26500
0!
#27000
b1001000000101001 &
1(
b10 1
0'
04
1!
#27500
0!
#28000
b0 &
0(
1$
b0 1
1!
#28500
0!
#29000
0$
b1 1
1'
14
b100 6
1!
#29500
0!
#30000
b1001000000101001 &
1(
b10 1
0'
04
1!
#30500
0!
#31000
b0 &
0(
1$
b0 1
1!
#31500
0!
#32000
0$
b1 1
1'
14
b100 6
1!
#32500
0!
#33000
b1001000000101001 &
1(
b10 1
0'
04
1!
#33500
0!
#34000
b0 &
0(
1$
b0 1
1!
#34500
0!
#35000
0$
b1 1
1'
14
b100 6
1!
#35500
0!
#36000
b1001000000101001 &
1(
b10 1
0'
04
1!
#36500
0!
#37000
b0 &
0(
1$
b0 1
1!
#37500
0!
#38000
0$
b1 1
1'
14
b100 6
1!
#38500
0!
#39000
b1001000000101001 &
1(
b10 1
0'
04
1!
#39500
0!
#40000
b0 &
0(
1$
b0 1
1!
#40500
0!
#41000
0$
b1 1
1'
14
b100 6
1!
#41500
0!
#42000
b1001000000101001 &
1(
b10 1
0'
04
1!
#42500
0!
#43000
b0 &
0(
1$
b0 1
1!
#43500
0!
#44000
0$
b1 1
1'
14
b100 6
1!
#44500
0!
#45000
b1001000000101001 &
1(
b10 1
0'
04
1!
#45500
0!
#46000
b0 &
0(
1$
b0 1
1!
#46500
0!
#47000
0$
b1 1
1'
14
b100 6
1!
#47500
0!
#48000
b1001000000101001 &
1(
b10 1
0'
04
1!
#48500
0!
#49000
b0 &
0(
1$
b0 1
1!
#49500
0!
#50000
0$
b1 1
1'
14
b100 6
1!
#50500
0!
#51000
b1001000000101001 &
1(
b10 1
0'
04
1!
#51500
0!
#52000
b0 &
0(
1$
b0 1
1!
#52500
0!
#53000
0$
b1 1
1'
14
b100 6
1!
#53500
0!
#54000
b1001000000101001 &
1(
b10 1
0'
04
1!
#54500
0!
#55000
b0 &
0(
1$
b0 1
1!
#55500
0!
#56000
0$
b1 1
1'
14
b100 6
1!
#56500
0!
#57000
b1001000000101001 &
1(
b10 1
0'
04
1!
#57500
0!
#58000
b0 &
0(
1$
b0 1
1!
#58500
0!
#59000
0$
b1 1
1'
14
b100 6
1!
#59500
0!
#60000
b1001000000101001 &
1(
b10 1
0'
04
1!
#60500
0!
#61000
b0 &
0(
1$
b0 1
1!
#61500
0!
#62000
0$
b1 1
1'
14
b100 6
1!
#62500
0!
#63000
b1001000000101001 &
1(
b10 1
0'
04
1!
#63500
0!
#64000
b0 &
0(
1$
b0 1
1!
#64500
0!
#65000
0$
b1 1
1'
14
b100 6
1!
#65500
0!
#66000
b1001000000101001 &
1(
b10 1
0'
04
1!
#66500
0!
#67000
b0 &
0(
1$
b0 1
1!
#67500
0!
#68000
0$
b1 1
1'
14
b100 6
1!
#68500
0!
#69000
b1001000000101001 &
1(
b10 1
0'
04
1!
#69500
0!
#70000
b0 &
0(
1$
b0 1
1!
#70500
0!
#71000
0$
b1 1
1'
14
b100 6
1!
#71500
0!
#72000
b1001000000101001 &
1(
b10 1
0'
04
1!
#72500
0!
#73000
b0 &
0(
1$
b0 1
1!
#73500
0!
#74000
0$
b1 1
1'
14
b100 6
1!
#74500
0!
#75000
b1001000000101001 &
1(
b10 1
0'
04
1!
#75500
0!
#76000
b0 &
0(
1$
b0 1
1!
#76500
0!
#77000
0$
b1 1
1'
14
b100 6
1!
#77500
0!
#78000
b1001000000101001 &
1(
b10 1
0'
04
1!
#78500
0!
#79000
b0 &
0(
1$
b0 1
1!
#79500
0!
#80000
0$
b1 1
1'
14
b100 6
1!
#80500
0!
#81000
b1001000000101001 &
1(
b10 1
0'
04
1!
#81500
0!
#82000
b0 &
0(
1$
b0 1
1!
#82500
0!
#83000
0$
b1 1
1'
14
b100 6
1!
#83500
0!
#84000
b1001000000101001 &
1(
b10 1
0'
04
1!
#84500
0!
#85000
b0 &
0(
1$
b0 1
1!
#85500
0!
#86000
0$
b1 1
1'
14
b100 6
1!
#86500
0!
#87000
b1001000000101001 &
1(
b10 1
0'
04
1!
#87500
0!
#88000
b0 &
0(
1$
b0 1
1!
#88500
0!
#89000
0$
b1 1
1'
14
b100 6
1!
#89500
0!
#90000
b1001000000101001 &
1(
b10 1
0'
04
1!
#90500
0!
#91000
b0 &
0(
1$
b0 1
1!
#91500
0!
#92000
0$
b1 1
1'
14
b100 6
1!
#92500
0!
#93000
b1001000000101001 &
1(
b10 1
0'
04
1!
#93500
0!
#94000
b0 &
0(
1$
b0 1
1!
#94500
0!
#95000
0$
b1 1
1'
14
b100 6
1!
#95500
0!
#96000
b1001000000101001 &
1(
b10 1
0'
04
1!
#96500
0!
#97000
b0 &
0(
1$
b0 1
1!
#97500
0!
#98000
0$
b1 1
1'
14
b100 6
1!
#98500
0!
#99000
b1001000000101001 &
1(
b10 1
0'
04
1!
#99500
0!
#100000
b0 &
0(
1$
b0 1
1!
#100500
0!
#101000
0$
b1 1
1'
14
b100 6
1!
#101500
0!
#102000
b1001000000101001 &
1(
b10 1
0'
04
1!
#102500
0!
#103000
b0 &
0(
1$
b0 1
1!
#103500
0!
#104000
0$
b1 1
1'
14
b100 6
1!
#104500
0!
#105000
b1001000000101001 &
1(
b10 1
0'
04
1!
#105500
0!
#106000
b0 &
0(
1$
b0 1
1!
#106500
0!
#107000
0$
b1 1
1'
14
b100 6
1!
#107500
0!
#108000
b1001000000101001 &
1(
b10 1
0'
04
1!
#108500
0!
#109000
b0 1
1!
