src/decoder/decoder.v
// ===========================================
// Decoder module for the Compute Unit
// 
// Conceptually, this module is essentially a "demuxer", breaking
// up an input signal into something "recognizable". This decoder
// will take in a 16 bit custom instruction part of our ISA and 
// will output the proper 
// ===========================================
module decoder #(
  parameter PC_ADDR_WIDTH = 8, 
            INST_MSG_WIDTH = 16
) (
  input clk,
  input reset,
  input [3:0] cu_state, 

  // Functional Inputs
  input [INST_MSG_WIDTH-1:0] instr, 

  // Decoded Outputs
  output [3:0] rd, 
  output [3:0] rs1, 
  output [3:0] rs2, 
  output [3:0] rimm, 
  output [7:0] imm, 
  output [3:0] alu_func,
  output [3:0] opcode,

  // Decoded Flags (Which instr to enable)
  output is_alu, // Includes both branches and alu ops
  output is_branch, // Separate branch flag here for the branching logic in PC
  output is_const, 
  output is_load, 
  output is_store,
  output is_nop,
  output is_jr // jump return flag to signal the end of an instruction. Process here

);

// Localparam encoding for our ISA
localparam  ADD = 4'd0, 
            SUB = 4'd1, 
            MUL = 4'd2, 
            DIV = 4'd3, 
            BNE = 4'd4, 
            BEQ = 4'd5,
            BLT = 4'd6, 
            BGT = 4'd7, 
            CONST = 4'd8,
            LW = 4'd9,
            SW = 4'd10,
            NOP = 4'd11,
            JR = 4'd12;

// ALU Local params
localparam  alu_add  = 4'd0, 
            alu_sub  = 4'd1, 
            alu_mul  = 4'd2, 
            alu_div  = 4'd3,
            alu_and  = 4'd4, 
            alu_or   = 4'd5, 
            alu_srl  = 4'd6, 
            alu_sll  = 4'd15,
            alu_cmp  = 4'd8;

localparam DECODE = 4'd2;

// Registering outputs
reg [3:0] rd_reg; 
reg [3:0] rs1_reg; 
reg [3:0] rs2_reg; 
reg [3:0] rimm_reg; 
reg [7:0] imm_reg; 
reg [3:0] alu_func_reg; 
reg is_alu_reg; 
reg is_branch_reg;
reg is_const_reg; 
reg is_load_reg; 
reg is_store_reg; 
reg is_nop_reg;
reg is_jr_reg; 
assign rd = rd_reg;
assign rs1 = rs1_reg;
assign rs2 = rs2_reg; 
assign rimm = rimm_reg; 
assign imm = imm_reg; 
assign alu_func = alu_func_reg; 
assign is_alu = is_alu_reg;
assign is_branch = is_branch_reg;
assign is_const = is_const_reg; 
assign is_load = is_load_reg;
assign is_store = is_store_reg; 
assign is_nop = is_nop_reg;
assign is_jr = is_jr_reg; 

// Internal registers
// wire [3:0] opcode; 
assign opcode = instr[15:12];

// Case Statement Logic
always @(posedge clk) begin 
  if (reset) begin 
    // Set all output signals to 0 
    rd_reg <= 0; 
    rs1_reg <= 0; 
    rs2_reg <= 0; 
    rimm_reg <= 0; 
    imm_reg <= 0; 
    alu_func_reg <= 0; 
    is_alu_reg <= 0; 
    is_branch_reg <= 0;
    is_const_reg <= 0; 
    is_load_reg <= 0; 
    is_store_reg <= 0; 
    is_jr_reg <= 0; 
  end else begin 
    if (cu_state == DECODE) begin 
      // Assigning initial values 
      rd_reg <= instr[11:8];
      rs1_reg <= instr[7:4]; 
      rs2_reg <= instr[3:0];
      rimm_reg <= instr[11:8];
      imm_reg <= instr[7:0];
      // Resetting Flags
      alu_func_reg <= 0; 
      is_alu_reg <= 0; 
      is_branch_reg <= 0;
      is_const_reg <= 0; 
      is_load_reg <= 0; 
      is_store_reg <= 0; 
      is_jr_reg <= 0; 
      case (opcode)
        ADD: begin 
          alu_func_reg <= alu_add; 
          is_alu_reg <= 1; 
        end
        SUB: begin 
          alu_func_reg <= alu_sub;
          is_alu_reg <= 1; 
        end
        MUL: begin 
          alu_func_reg <= alu_mul;
          is_alu_reg <= 1; 
        end
        DIV: begin 
          alu_func_reg <= alu_div;
          is_alu_reg <= 1; 
        end
        BNE: begin 
          alu_func_reg <= alu_cmp;
          is_alu_reg <= 1; 
          is_branch_reg <= 1;
        end
        BEQ: begin 
          alu_func_reg <= alu_cmp;
          is_alu_reg <= 1; 
          is_branch_reg <= 1;
        end
        BLT: begin 
          alu_func_reg <= alu_cmp;
          is_alu_reg <= 1; 
          is_branch_reg <= 1;
        end
        BGT: begin 
          alu_func_reg <= alu_cmp;
          is_alu_reg <= 1; 
          is_branch_reg <= 1;
        end
        CONST: begin 
          is_const_reg <= 1;
        end
        LW: begin 
          is_load_reg <= 1;
        end
        SW: begin 
          is_store_reg <= 1;
        end
        NOP: begin 
          is_nop_reg <= 1;
        end
        JR: begin 
          is_jr_reg <= 1;
        end
      endcase
    end
  end
end

endmodule

wrapper/decoder/wrapper_decoder.v
`include "../../src/decoder/decoder.v"
module wrapper_decoder #(
  parameter PC_ADDR_WIDTH = 8, 
            INST_MSG_WIDTH = 16
) (
  input clk,
  input reset,
  input [3:0] cu_state, 

  // Functional Inputs
  input [INST_MSG_WIDTH-1:0] instr, 

  // Decoded Outputs
  output [3:0] rd, 
  output [3:0] rs1, 
  output [3:0] rs2, 
  output [3:0] rimm, 
  output [7:0] imm, 
  output [3:0] alu_func,

  // Decoded Flags (Which instr to enable)
  output is_alu, // Includes both branches and alu ops
  output is_branch, // Separate branch flag here for the branching logic in PC
  output is_const, 
  output is_load, 
  output is_store,
  output is_nop,
  output is_jr // jump return flag to signal the end of an instruction. Process here

);

decoder #(8, 16) inst_decoder(
  .clk(clk),
  .reset(reset),
  .cu_state(cu_state),
  .instr(instr),
  .rd(rd),
  .rs1(rs1),
  .rs2(rs2),
  .rimm(rimm),
  .imm(imm),
  .alu_func(alu_func),
  .is_alu(is_alu),
  .is_branch(is_branch),
  .is_const(is_const),
  .is_load(is_load),
  .is_store(is_store),
  .is_nop(is_nop),
  .is_jr(is_jr)
);

// Dumping vcd
initial begin 
  $dumpfile("decoder_dump.vcd");
  $dumpvars(1, wrapper_decoder);
end

endmodule

test/decoder_test/decoder_dump.vcd
$date
	Mon Jan  6 16:32:19 2025
$end
$version
	Icarus Verilog
$end
$timescale
	1ps
$end
$scope module wrapper_decoder $end
$var wire 1 ! clk $end
$var wire 4 " cu_state [3:0] $end
$var wire 16 # instr [15:0] $end
$var wire 1 $ reset $end
$var wire 4 % rs2 [3:0] $end
$var wire 4 & rs1 [3:0] $end
$var wire 4 ' rimm [3:0] $end
$var wire 4 ( rd [3:0] $end
$var wire 1 ) is_store $end
$var wire 1 * is_nop $end
$var wire 1 + is_load $end
$var wire 1 , is_jr $end
$var wire 1 - is_const $end
$var wire 1 . is_branch $end
$var wire 1 / is_alu $end
$var wire 8 0 imm [7:0] $end
$var wire 4 1 alu_func [3:0] $end
$var parameter 32 2 INST_MSG_WIDTH $end
$var parameter 32 3 PC_ADDR_WIDTH $end
$upscope $end
$enddefinitions $end
$comment Show the parameter values. $end
$dumpall
b1000 3
b10000 2
$end
#0
$dumpvars
bx 1
bx 0
x/
x.
x-
x,
x+
x*
x)
bx (
bx '
bx &
bx %
0$
bz #
bz "
1!
$end
#500
0!
#1000
1!
#1500
0!
#2000
1!
#2500
0!
#3000
1!
#3500
0!
#4000
1!
#4500
0!
#5000
1!
#5500
0!
#6000
1!
#6500
0!
#7000
1!
#7500
0!
#8000
1!
#8500
0!
#9000
1!
#9500
0!
#10000
b0 '
0,
0)
0+
0-
0.
0/
b0 1
b0 0
b0 %
b0 &
b0 (
1!
1$
#10500
0!
#11000
1!
#11500
0!
#12000
1!
#12500
0!
#13000
1!
#13500
0!
#14000
1!
#14500
0!
#15000
1!
#15500
0!
#16000
1!
#16500
0!
#17000
1!
#17500
0!
#18000
1!
#18500
0!
#19000
1!
#19500
0!
#20000
b1 '
1/
b10000100 0
b100 %
b1000 &
b1 (
1!
b110000100 #
b10 "
0$
#20500
0!
#21000
1/
1!
#21500
0!
#22000
1/
1!
#22500
0!
#23000
1/
1!
#23500
0!
#24000
1/
1!
#24500
0!
#25000
1/
1!
#25500
0!
#26000
1/
1!
#26500
0!
#27000
1/
1!
#27500
0!
#28000
1/
1!
#28500
0!
#29000
1/
1!
#29500
0!
#30000
1/
1!
#30500
0!
#31000
1/
1!
#31500
0!
#32000
1/
1!
#32500
0!
#33000
1/
1!
#33500
0!
#34000
1/
1!
#34500
0!
#35000
1/
1!
#35500
0!
#36000
1/
1!
#36500
0!
#37000
1/
1!
#37500
0!
#38000
1/
1!
#38500
0!
#39000
1/
1!
#39500
0!
#40000
b0 '
0/
b0 0
b0 %
b0 &
b0 (
1!
1$
#40500
0!
#41000
1!
#41500
0!
#42000
1!
#42500
0!
#43000
1!
#43500
0!
#44000
1!
#44500
0!
#45000
1!
#45500
0!
#46000
1!
#46500
0!
#47000
1!
#47500
0!
#48000
1!
#48500
0!
#49000
1!
#49500
0!
#50000
b10 '
1/
b1 1
b1010111 0
b111 %
b101 &
b10 (
1!
b1001001010111 #
0$
#50500
0!
#51000
1/
b1 1
1!
#51500
0!
#52000
1/
b1 1
1!
#52500
0!
#53000
1/
b1 1
1!
#53500
0!
#54000
1/
b1 1
1!
#54500
0!
#55000
1/
b1 1
1!
#55500
0!
#56000
1/
b1 1
1!
#56500
0!
#57000
1/
b1 1
1!
#57500
0!
#58000
1/
b1 1
1!
#58500
0!
#59000
1/
b1 1
1!
#59500
0!
#60000
1/
b1 1
1!
#60500
0!
#61000
1/
b1 1
1!
#61500
0!
#62000
1/
b1 1
1!
#62500
0!
#63000
1/
b1 1
1!
#63500
0!
#64000
1/
b1 1
1!
#64500
0!
#65000
1/
b1 1
1!
#65500
0!
#66000
1/
b1 1
1!
#66500
0!
#67000
1/
b1 1
1!
#67500
0!
#68000
1/
b1 1
1!
#68500
0!
#69000
1/
b1 1
1!
#69500
0!
#70000
b0 '
0/
b0 1
b0 0
b0 %
b0 &
b0 (
1!
1$
#70500
0!
#71000
1!
#71500
0!
#72000
1!
#72500
0!
#73000
1!
#73500
0!
#74000
1!
#74500
0!
#75000
1!
#75500
0!
#76000
1!
#76500
0!
#77000
1!
#77500
0!
#78000
1!
#78500
0!
#79000
1!
#79500
0!
#80000
b1010 '
1.
1/
b1000 1
b1 0
b1 %
b1010 (
1!
b101101000000001 #
0$
#80500
0!
#81000
1.
1/
b1000 1
1!
#81500
0!
#82000
1.
1/
b1000 1
1!
#82500
0!
#83000
1.
1/
b1000 1
1!
#83500
0!
#84000
1.
1/
b1000 1
1!
#84500
0!
#85000
1.
1/
b1000 1
1!
#85500
0!
#86000
1.
1/
b1000 1
1!
#86500
0!
#87000
1.
1/
b1000 1
1!
#87500
0!
#88000
1.
1/
b1000 1
1!
#88500
0!
#89000
1.
1/
b1000 1
1!
#89500
0!
#90000
1.
1/
b1000 1
1!
#90500
0!
#91000
1.
1/
b1000 1
1!
#91500
0!
#92000
1.
1/
b1000 1
1!
#92500
0!
#93000
1.
1/
b1000 1
1!
#93500
0!
#94000
1.
1/
b1000 1
1!
#94500
0!
#95000
1.
1/
b1000 1
1!
#95500
0!
#96000
1.
1/
b1000 1
1!
#96500
0!
#97000
1.
1/
b1000 1
1!
#97500
0!
#98000
1.
1/
b1000 1
1!
#98500
0!
#99000
1.
1/
b1000 1
1!
#99500
0!
#100000
b0 '
0.
0/
b0 1
b0 0
b0 %
b0 (
1!
1$
#100500
0!
#101000
1!
#101500
0!
#102000
1!
#102500
0!
#103000
1!
#103500
0!
#104000
1!
#104500
0!
#105000
1!
#105500
0!
#106000
1!
#106500
0!
#107000
1!
#107500
0!
#108000
1!
#108500
0!
#109000
1!
#109500
0!
#110000
b110 '
1-
b10101010 0
b1010 %
b1010 &
b110 (
1!
b1000011010101010 #
0$
#110500
0!
#111000
1-
1!
#111500
0!
#112000
1-
1!
#112500
0!
#113000
1-
1!
#113500
0!
#114000
1-
1!
#114500
0!
#115000
1-
1!
#115500
0!
#116000
1-
1!
#116500
0!
#117000
1-
1!
#117500
0!
#118000
1-
1!
#118500
0!
#119000
1-
1!
#119500
0!
#120000
1-
1!
#120500
0!
#121000
1-
1!
#121500
0!
#122000
1-
1!
#122500
0!
#123000
1-
1!
#123500
0!
#124000
1-
1!
#124500
0!
#125000
1-
1!
#125500
0!
#126000
1-
1!
#126500
0!
#127000
1-
1!
#127500
0!
#128000
1-
1!
#128500
0!
#129000
1-
1!
#129500
0!
#130000
b0 '
0-
b0 0
b0 %
b0 &
b0 (
1!
1$
#130500
0!
#131000
1!
#131500
0!
#132000
1!
#132500
0!
#133000
1!
#133500
0!
#134000
1!
#134500
0!
#135000
1!
#135500
0!
#136000
1!
#136500
0!
#137000
1!
#137500
0!
#138000
1!
#138500
0!
#139000
1!
#139500
0!
#140000
1+
b110101 0
b101 %
b11 &
1!
b1001000000110101 #
0$
#140500
0!
#141000
1+
1!
#141500
0!
#142000
1+
1!
#142500
0!
#143000
1+
1!
#143500
0!
#144000
1+
1!
#144500
0!
#145000
1+
1!
#145500
0!
#146000
1+
1!
#146500
0!
#147000
1+
1!
#147500
0!
#148000
1+
1!
#148500
0!
#149000
1+
1!
#149500
0!
#150000
1+
1!
#150500
0!
#151000
1+
1!
#151500
0!
#152000
1+
1!
#152500
0!
#153000
1+
1!
#153500
0!
#154000
1+
1!
#154500
0!
#155000
1+
1!
#155500
0!
#156000
1+
1!
#156500
0!
#157000
1+
1!
#157500
0!
#158000
1+
1!
#158500
0!
#159000
1+
1!
#159500
0!
#160000
0+
b0 0
b0 %
b0 &
1!
1$
#160500
0!
#161000
1!
#161500
0!
#162000
1!
#162500
0!
#163000
1!
#163500
0!
#164000
1!
#164500
0!
#165000
1!
#165500
0!
#166000
1!
#166500
0!
#167000
1!
#167500
0!
#168000
1!
#168500
0!
#169000
1!
#169500
0!
#170000
1)
b1001111 0
b1111 %
b100 &
1!
b1010000001001111 #
0$
#170500
0!
#171000
1)
1!
#171500
0!
#172000
1)
1!
#172500
0!
#173000
1)
1!
#173500
0!
#174000
1)
1!
#174500
0!
#175000
1)
1!
#175500
0!
#176000
1)
1!
#176500
0!
#177000
1)
1!
#177500
0!
#178000
1)
1!
#178500
0!
#179000
1)
1!
#179500
0!
#180000
1)
1!
#180500
0!
#181000
1)
1!
#181500
0!
#182000
1)
1!
#182500
0!
#183000
1)
1!
#183500
0!
#184000
1)
1!
#184500
0!
#185000
1)
1!
#185500
0!
#186000
1)
1!
#186500
0!
#187000
1)
1!
#187500
0!
#188000
1)
1!
#188500
0!
#189000
1)
1!
#189500
0!
#190000
0)
b0 0
b0 %
b0 &
1!
1$
#190500
0!
#191000
1!
#191500
0!
#192000
1!
#192500
0!
#193000
1!
#193500
0!
#194000
1!
#194500
0!
#195000
1!
#195500
0!
#196000
1!
#196500
0!
#197000
1!
#197500
0!
#198000
1!
#198500
0!
#199000
1!
#199500
0!
#200000
1*
1!
b1011000000000000 #
0$
#200500
0!
#201000
1!
#201500
0!
#202000
1!
#202500
0!
#203000
1!
#203500
0!
#204000
1!
#204500
0!
#205000
1!
#205500
0!
#206000
1!
#206500
0!
#207000
1!
#207500
0!
#208000
1!
#208500
0!
#209000
1!
#209500
0!
#210000
1!
#210500
0!
#211000
1!
#211500
0!
#212000
1!
#212500
0!
#213000
1!
#213500
0!
#214000
1!
#214500
0!
#215000
1!
#215500
0!
#216000
1!
#216500
0!
#217000
1!
#217500
0!
#218000
1!
#218500
0!
#219000
1!
#219500
0!
#220000
1!
1$
#220500
0!
#221000
1!
#221500
0!
#222000
1!
#222500
0!
#223000
1!
#223500
0!
#224000
1!
#224500
0!
#225000
1!
#225500
0!
#226000
1!
#226500
0!
#227000
1!
#227500
0!
#228000
1!
#228500
0!
#229000
1!
#229500
0!
#230000
1,
1!
b1100000000000000 #
0$
#230500
0!
#231000
1,
1!
#231500
0!
#232000
1,
1!
#232500
0!
#233000
1,
1!
#233500
0!
#234000
1,
1!
#234500
0!
#235000
1,
1!
#235500
0!
#236000
1,
1!
#236500
0!
#237000
1,
1!
#237500
0!
#238000
1,
1!
#238500
0!
#239000
1,
1!
