src/alu/alu.v
// ===========================================
// Scalar ALU Design for a Compute Unit
// - Support 8 bit arithmetic & logical ops
// - Will also contain comparison flags
// - Supports the following instructions: 
//   Arith: ADD, SUB, MUL, DIV 
//   Logic: AND, OR, XOR
//   Shift: SRL, SLL, SRA
//   Comp : CMP 
// - WILL NOT SUPPORT CARRY 
// ===========================================

module alu (
  input clk, 
  input reset, 

  // Functionality inputs
  input alu_en, 
  input [3:0] alu_func, 
  input [15:0] a, 
  input [15:0] b, 

  // Functionality Outputs
  output [15:0] out, 

  // Comparison Flag Outputs
  output cmp_lt, 
  output cmp_eq
); 

// Establishing localparams for alu functions
localparam  alu_add  = 4'd0, 
            alu_sub  = 4'd1, 
            alu_mul  = 4'd2, 
            alu_div  = 4'd3,
            alu_and  = 4'd4, 
            alu_or   = 4'd5, 
            alu_srl  = 4'd6, 
            alu_sll  = 4'd15,
            alu_cmp  = 4'd8;

// Internal Register to work with all of our functionality
reg [15:0] alu_reg_out;
reg cmp_reg_eq;
reg cmp_reg_lt; 
reg cmp_reg_lte;
assign out = alu_reg_out; 
assign cmp_eq = cmp_reg_eq; 
assign cmp_lt = cmp_reg_lt; 
assign cmp_lte = cmp_reg_lte; 

// Case statements to process the different scenarios
always @(posedge clk) begin 
  // First check if we reset
  if (reset) begin 
    alu_reg_out <= 0; 
    cmp_reg_lt <= 0; 
    cmp_reg_lte <= 0; 
    cmp_reg_eq <= 0; 
  end
  else if (alu_en) begin 
    // Case statement here to perform the correct alu operation on our output
    // Data on inputs a and b are assumed to be signed inputs
    case (alu_func) 

      alu_add : alu_reg_out <= a + b; 
      alu_sub : alu_reg_out <= a - b; 
      alu_mul : alu_reg_out <= a * b; 
      alu_div : alu_reg_out <= a / b;
      alu_and : alu_reg_out <= a & b;
      alu_or  : alu_reg_out <= a | b;
      alu_srl : alu_reg_out <= a & b;
      alu_sll : alu_reg_out <= $signed(a) << $unsigned(b[3:0]);
      alu_srl : alu_reg_out <= $signed(a) >> $unsigned(b[3:0]);
      alu_cmp : begin 
        alu_reg_out <= 0;
        cmp_reg_lt <= $signed(a) < $signed(b);
        cmp_reg_eq <= $signed(a) == $signed(b);
      end

      default : alu_reg_out <= 0; 
    endcase
  end

end



endmodule

wrapper/alu/wrapper_alu.v
// ===========================================
// Wrapper module for the ALU to enable waveforms
// ===========================================
// `timescale 1ns/1ps
`include "../../src/alu/alu.v"

module wrapper_alu (
  input clk, 
  input reset, 

  // Functionality inputs
  input alu_en, 
  input [3:0] alu_func, 
  input [15:0] a, 
  input [15:0] b, 

  // Functionality Outputs
  output [15:0] out, 

  // Comparison Flag Outputs
  output cmp_lt, 
  output cmp_eq
); 

alu inst_alu(
  .clk(clk),
  .reset(reset),
  .alu_en(alu_en),
  .alu_func(alu_func),
  .a(a),
  .b(b),
  .out(out),
  .cmp_lt(cmp_lt),
  .cmp_eq(cmp_eq)
);

// Dump waves
initial begin 
  $dumpfile("minigpu_alu.vcd");
  $dumpvars(1, wrapper_alu);
end

endmodule

test/alu_test/minigpu_alu.vcd
$date
	Thu Jan  2 15:29:17 2025
$end
$version
	Icarus Verilog
$end
$timescale
	1ps
$end
$scope module wrapper_alu $end
$var wire 16 ! a [15:0] $end
$var wire 1 " alu_en $end
$var wire 4 # alu_func [3:0] $end
$var wire 16 $ b [15:0] $end
$var wire 1 % clk $end
$var wire 1 & reset $end
$var wire 16 ' out [15:0] $end
$var wire 1 ( cmp_lt $end
$var wire 1 ) cmp_eq $end
$upscope $end
$enddefinitions $end
$comment Show the parameter values. $end
$dumpall
$end
#0
$dumpvars
x)
x(
b1010 '
z&
1%
b1010 $
b0 #
1"
b0 !
$end
#500
0%
#1000
1%
#1500
0%
#2000
1%
#2500
0%
#3000
1%
#3500
0%
#4000
1%
#4500
0%
#5000
1%
#5500
0%
#6000
1%
#6500
0%
#7000
1%
#7500
0%
#8000
1%
#8500
0%
#9000
1%
#9500
0%
#10000
b0 '
1%
b1111111111111111 $
b1 !
#10500
0%
#11000
1%
#11500
0%
#12000
1%
#12500
0%
#13000
1%
#13500
0%
#14000
1%
#14500
0%
#15000
1%
#15500
0%
#16000
1%
#16500
0%
#17000
1%
#17500
0%
#18000
1%
#18500
0%
#19000
1%
#19500
0%
#20000
b101 '
1%
b11 $
b10 !
#20500
0%
#21000
1%
#21500
0%
#22000
1%
#22500
0%
#23000
1%
#23500
0%
#24000
1%
#24500
0%
#25000
1%
#25500
0%
#26000
1%
#26500
0%
#27000
1%
#27500
0%
#28000
1%
#28500
0%
#29000
1%
#29500
0%
#30000
b1000 '
1%
b101 $
b11 !
#30500
0%
#31000
1%
#31500
0%
#32000
1%
#32500
0%
#33000
1%
#33500
0%
#34000
1%
#34500
0%
#35000
1%
#35500
0%
#36000
1%
#36500
0%
#37000
1%
#37500
0%
#38000
1%
#38500
0%
#39000
1%
#39500
0%
#40000
b1111111111110011 '
1%
b1111111111111000 $
b1111111111111011 !
#40500
0%
#41000
1%
#41500
0%
#42000
1%
#42500
0%
#43000
1%
#43500
0%
#44000
1%
#44500
0%
#45000
1%
#45500
0%
#46000
1%
#46500
0%
#47000
1%
#47500
0%
#48000
1%
#48500
0%
#49000
1%
#49500
0%
#50000
b1010 '
1%
b10100 $
b1111111111110110 !
#50500
0%
#51000
1%
#51500
0%
#52000
1%
#52500
0%
#53000
1%
#53500
0%
#54000
1%
#54500
0%
#55000
1%
#55500
0%
#56000
1%
#56500
0%
#57000
1%
#57500
0%
#58000
1%
#58500
0%
#59000
1%
#59500
0%
#60001
b1111111111111000 '
b1111111111111111 $
b1111111111111001 !
1%
#60501
0%
#61001
1%
#61501
0%
#62001
1%
#62501
0%
#63001
1%
#63501
0%
#64001
b1111111111111111 '
1%
b1110 $
b1111111111110001 !
#64501
0%
#65001
1%
#65501
0%
#66001
1%
#66501
0%
#67001
1%
#67501
0%
#68001
b100 '
1%
b1100 $
b1111111111111000 !
#68501
0%
#69001
1%
#69501
0%
#70001
1%
#70501
0%
#71001
1%
#71501
0%
#72001
b1111111111101001 '
1%
b1111111111110101 $
b1111111111110100 !
#72501
0%
#73001
1%
#73501
0%
#74001
1%
#74501
0%
#75001
1%
#75501
0%
#76001
b1111111111110101 '
1%
b1111111111110111 $
b1111111111111110 !
#76501
0%
#77001
1%
#77501
0%
#78001
1%
#78501
0%
#79001
1%
#79501
0%
#80001
b100 '
1%
b1111111111110101 $
b1111 !
#80501
0%
#81001
1%
#81501
0%
#82001
1%
#82501
0%
#83001
1%
#83501
0%
#84001
b1111111111111111 '
1%
b1 $
b1111111111111110 !
#84501
0%
#85001
1%
#85501
0%
#86001
1%
#86501
0%
#87001
1%
#87501
0%
#88001
b1111111111100110 '
1%
b1111111111110000 $
b1111111111110110 !
#88501
0%
#89001
1%
#89501
0%
#90001
1%
#90501
0%
#91001
1%
#91501
0%
#92001
b1111111111101111 '
1%
b1111111111110101 $
b1111111111111010 !
#92501
0%
#93001
1%
#93501
0%
#94001
1%
#94501
0%
#95001
1%
#95501
0%
#96001
b1111111111110001 '
1%
b1111111111110011 $
b1111111111111110 !
#96501
0%
#97001
1%
#97501
0%
#98001
1%
#98501
0%
#99001
1%
#99501
0%
#100002
b0 '
b10 #
b1010 $
b0 !
1%
#100502
0%
#101002
1%
#101502
0%
#102002
1%
#102502
0%
#103002
1%
#103502
0%
#104002
1%
#104502
0%
#105002
1%
#105502
0%
#106002
1%
#106502
0%
#107002
1%
#107502
0%
#108002
1%
#108502
0%
#109002
1%
#109502
0%
#110002
b1111111111111111 '
1%
b1111111111111111 $
b1 !
#110502
0%
#111002
1%
#111502
0%
#112002
1%
#112502
0%
#113002
1%
#113502
0%
#114002
1%
#114502
0%
#115002
1%
#115502
0%
#116002
1%
#116502
0%
#117002
1%
#117502
0%
#118002
1%
#118502
0%
#119002
1%
#119502
0%
#120002
b110 '
1%
b11 $
b10 !
#120502
0%
#121002
1%
#121502
0%
#122002
1%
#122502
0%
#123002
1%
#123502
0%
#124002
1%
#124502
0%
#125002
1%
#125502
0%
#126002
1%
#126502
0%
#127002
1%
#127502
0%
#128002
1%
#128502
0%
#129002
1%
#129502
0%
#130002
b1111 '
1%
b101 $
b11 !
#130502
0%
#131002
1%
#131502
0%
#132002
1%
#132502
0%
#133002
1%
#133502
0%
#134002
1%
#134502
0%
#135002
1%
#135502
0%
#136002
1%
#136502
0%
#137002
1%
#137502
0%
#138002
1%
#138502
0%
#139002
1%
#139502
0%
#140002
b101000 '
1%
b1111111111111000 $
b1111111111111011 !
#140502
0%
#141002
1%
#141502
0%
#142002
1%
#142502
0%
#143002
1%
#143502
0%
#144002
1%
#144502
0%
#145002
1%
#145502
0%
#146002
1%
#146502
0%
#147002
1%
#147502
0%
#148002
1%
#148502
0%
#149002
1%
#149502
0%
#150002
b1111111100111000 '
1%
b10100 $
b1111111111110110 !
#150502
0%
#151002
1%
#151502
0%
#152002
1%
#152502
0%
#153002
1%
#153502
0%
#154002
1%
#154502
0%
#155002
1%
#155502
0%
#156002
1%
#156502
0%
#157002
1%
#157502
0%
#158002
1%
#158502
0%
#159002
1%
#159502
0%
#160003
b1111111110110101 '
b101 $
b1111111111110001 !
1%
#160503
0%
#161003
1%
#161503
0%
#162003
1%
#162503
0%
#163003
1%
#163503
0%
#164003
b1111111110101000 '
1%
b1111111111110101 $
b1000 !
#164503
0%
#165003
1%
#165503
0%
#166003
1%
#166503
0%
#167003
1%
#167503
0%
#168003
b10100 '
1%
b10 $
b1010 !
#168503
0%
#169003
1%
#169503
0%
#170003
1%
#170503
0%
#171003
1%
#171503
0%
#172003
b1111111111010011 '
1%
b1111111111111011 $
b1001 !
#172503
0%
#173003
1%
#173503
0%
#174003
1%
#174503
0%
#175003
1%
#175503
0%
#176003
b1111111111111001 '
1%
b111 $
b1111111111111111 !
#176503
0%
#177003
1%
#177503
0%
#178003
1%
#178503
0%
#179003
1%
#179503
0%
#180003
b11110 '
1%
b1111 $
b10 !
#180503
0%
#181003
1%
#181503
0%
#182003
1%
#182503
0%
#183003
1%
#183503
0%
#184003
b1111111111110010 '
1%
b1111111111111110 $
b111 !
#184503
0%
#185003
1%
#185503
0%
#186003
1%
#186503
0%
#187003
1%
#187503
0%
#188003
b100000 '
1%
b1111111111111100 $
b1111111111111000 !
#188503
0%
#189003
1%
#189503
0%
#190003
1%
#190503
0%
#191003
1%
#191503
0%
#192003
b1111111111110110 '
1%
b1111111111111011 $
b10 !
#192503
0%
#193003
1%
#193503
0%
#194003
1%
#194503
0%
#195003
1%
#195503
0%
#196003
b10010000 '
1%
b1111111111110100 $
b1111111111110100 !
#196503
0%
#197003
1%
#197503
0%
#198003
1%
#198503
0%
#199003
1%
#199503
0%
#200003
b1110 '
1%
b1111111111111110 $
b1111111111111001 !
#200503
0%
#201003
1%
#201503
0%
#202003
1%
#202503
0%
#203003
1%
#203503
0%
#204003
b111 '
1%
b1111111111111001 $
b1111111111111111 !
#204503
0%
#205003
1%
#205503
0%
#206003
1%
#206503
0%
#207003
1%
#207503
0%
#208003
b1111111111011100 '
1%
b1111111111111101 $
b1100 !
#208503
0%
#209003
1%
#209503
0%
#210003
1%
#210503
0%
#211003
1%
#211503
0%
#212003
b0 '
1%
b1111111111110100 $
b0 !
#212503
0%
#213003
1%
#213503
0%
#214003
1%
#214503
0%
#215003
1%
#215503
0%
#216003
b1111111111110000 '
1%
b1000 $
b1111111111111110 !
#216503
0%
#217003
1%
#217503
0%
#218003
1%
#218503
0%
#219003
1%
#219503
0%
#220003
1%
b1111111111111100 $
b100 !
#220503
0%
#221003
1%
#221503
0%
#222003
1%
#222503
0%
#223003
1%
#223503
0%
#224003
b1111000 '
1%
b1000 $
b1111 !
#224503
0%
#225003
1%
#225503
0%
#226003
1%
#226503
0%
#227003
1%
#227503
0%
#228003
b1111111111101010 '
1%
b1111111111110101 $
b10 !
#228503
0%
#229003
1%
#229503
0%
#230003
1%
#230503
0%
#231003
1%
#231503
0%
#232003
b101100 '
1%
b100 $
b1011 !
#232503
0%
#233003
1%
#233503
0%
#234003
1%
#234503
0%
#235003
1%
#235503
0%
#236003
b1111111110100000 '
1%
b1000 $
b1111111111110100 !
#236503
0%
#237003
1%
#237503
0%
#238003
1%
#238503
0%
#239003
1%
#239503
0%
#240003
b1111111100011111 '
1%
b1111 $
b1111111111110001 !
#240503
0%
#241003
1%
#241503
0%
#242003
1%
#242503
0%
#243003
1%
#243503
0%
#244003
b1111 '
1%
b11 $
b101 !
#244503
0%
#245003
1%
#245503
0%
#246003
1%
#246503
0%
#247003
1%
#247503
0%
#248003
b1101100 '
1%
b1001 $
b1100 !
#248503
0%
#249003
1%
#249503
0%
#250003
1%
#250503
0%
#251003
1%
#251503
0%
#252003
b1111111111101000 '
1%
b100 $
b1111111111111010 !
#252503
0%
#253003
1%
#253503
0%
#254003
1%
#254503
0%
#255003
1%
#255503
0%
#256003
b110111 '
1%
b1111111111111011 $
b1111111111110101 !
#256503
0%
#257003
1%
#257503
0%
#258003
1%
#258503
0%
#259003
1%
#259503
0%
#260003
b0 '
1%
b101 $
b0 !
#260503
0%
#261003
1%
#261503
0%
#262003
1%
#262503
0%
#263003
1%
#263503
0%
#264003
b1111111111110100 '
1%
b1111111111111111 $
b1100 !
#264503
0%
#265003
1%
#265503
0%
#266003
1%
#266503
0%
#267003
1%
#267503
0%
#268003
b1111111111110000 '
1%
b1000 $
b1111111111111110 !
#268503
0%
#269003
1%
#269503
0%
#270003
1%
#270503
0%
#271003
1%
#271503
0%
#272003
b1111111111101000 '
1%
b1111111111111010 $
b100 !
#272503
0%
#273003
1%
#273503
0%
#274003
1%
#274503
0%
#275003
1%
#275503
0%
#276003
b1100011 '
1%
b1011 $
b1001 !
#276503
0%
#277003
1%
#277503
0%
#278003
1%
#278503
0%
#279003
1%
#279503
0%
#280003
b1111111111110001 '
1%
b1111 $
b1111111111111111 !
#280503
0%
#281003
1%
#281503
0%
#282003
1%
#282503
0%
#283003
1%
#283503
0%
#284003
b1 '
1%
b1111111111111111 $
#284503
0%
#285003
1%
#285503
0%
#286003
1%
#286503
0%
#287003
1%
#287503
0%
#288003
b1111111111001010 '
1%
b1001 $
b1111111111111010 !
#288503
0%
#289003
1%
#289503
0%
#290003
1%
#290503
0%
#291003
1%
#291503
0%
#292003
b1000010 '
1%
b110 $
b1011 !
#292503
0%
#293003
1%
#293503
0%
#294003
1%
#294503
0%
#295003
1%
#295503
0%
#296003
b1111111110100110 '
1%
b1111111111110111 $
b1010 !
#296503
0%
#297003
1%
#297503
0%
#298003
1%
#298503
0%
#299003
1%
#299503
0%
#300003
b10000010 '
1%
b1010 $
b1101 !
#300503
0%
#301003
1%
#301503
0%
#302003
1%
#302503
0%
#303003
1%
#303503
0%
#304003
b1111111111110100 '
1%
b11 $
b1111111111111100 !
#304503
0%
#305003
1%
#305503
0%
#306003
1%
#306503
0%
#307003
1%
#307503
0%
#308003
b1001000 '
1%
b1100 $
b110 !
#308503
0%
#309003
1%
#309503
0%
#310003
1%
#310503
0%
#311003
1%
#311503
0%
#312003
b1111111111100010 '
1%
b110 $
b1111111111111011 !
#312503
0%
#313003
1%
#313503
0%
#314003
1%
#314503
0%
#315003
1%
#315503
0%
#316003
b11010 '
1%
b1111111111110011 $
b1111111111111110 !
#316503
0%
#317003
1%
#317503
0%
#318003
1%
#318503
0%
#319003
1%
#319503
0%
#320003
b10110000 '
1%
b1111111111110101 $
b1111111111110000 !
#320503
0%
#321003
1%
#321503
0%
#322003
1%
#322503
0%
#323003
1%
#323503
0%
#324003
b1111111110111010 '
1%
b1110 $
b1111111111111011 !
#324503
0%
#325003
1%
#325503
0%
#326003
1%
#326503
0%
#327003
1%
#327503
0%
#328003
b1111111110110101 '
1%
b1111 $
#328503
0%
#329003
1%
#329503
0%
#330003
1%
#330503
0%
#331003
1%
#331503
0%
#332003
b0 '
1%
b0 $
b111 !
#332503
0%
#333003
1%
#333503
0%
#334003
1%
#334503
0%
#335003
1%
#335503
0%
#336003
b1111111110111000 '
1%
b1000 $
b1111111111110111 !
#336503
0%
#337003
1%
#337503
0%
#338003
1%
#338503
0%
#339003
1%
#339503
0%
#340003
b1111111111110001 '
1%
b1 $
b1111111111110001 !
#340503
0%
#341003
1%
#341503
0%
#342003
1%
#342503
0%
#343003
1%
#343503
0%
#344003
b10100 '
1%
b1111111111111110 $
b1111111111110110 !
#344503
0%
#345003
1%
#345503
0%
#346003
1%
#346503
0%
#347003
1%
#347503
0%
#348003
b1111111110001000 '
1%
b1111111111111000 $
b1111 !
#348503
0%
#349003
1%
#349503
0%
#350003
1%
#350503
0%
#351003
1%
#351503
0%
#352003
b10010000 '
1%
b1100 $
b1100 !
#352503
0%
#353003
1%
#353503
0%
#354003
1%
#354503
0%
#355003
1%
#355503
0%
#356003
b1111111111110000 '
1%
b1111111111111110 $
b1000 !
#356503
0%
#357003
1%
#357503
0%
#358003
1%
#358503
0%
#359003
1%
#359503
0%
#360003
b1000 '
1%
b1111111111111100 $
b1111111111111110 !
#360503
0%
#361003
1%
#361503
0%
#362003
1%
#362503
0%
#363003
1%
#363503
0%
#364003
b110 '
1%
b10 $
b11 !
#364503
0%
#365003
1%
#365503
0%
#366003
1%
#366503
0%
#367003
1%
#367503
0%
#368003
b1000110 '
1%
b1010 $
b111 !
#368503
0%
#369003
1%
#369503
0%
#370003
1%
#370503
0%
#371003
1%
#371503
0%
#372003
b0 '
1%
b0 $
b1111111111111110 !
#372503
0%
#373003
1%
#373503
0%
#374003
1%
#374503
0%
#375003
1%
#375503
0%
#376003
b1110101 '
1%
b1101 $
b1001 !
#376503
0%
#377003
1%
#377503
0%
#378003
1%
#378503
0%
#379003
1%
#379503
0%
#380003
b100000 '
1%
b100 $
b1000 !
#380503
0%
#381003
1%
#381503
0%
#382003
1%
#382503
0%
#383003
1%
#383503
0%
#384003
b1111111111011100 '
1%
b1111111111111100 $
b1001 !
#384503
0%
#385003
1%
#385503
0%
#386003
1%
#386503
0%
#387003
1%
#387503
0%
#388003
b1111111111001010 '
1%
b1111111111110111 $
b110 !
#388503
0%
#389003
1%
#389503
0%
#390003
1%
#390503
0%
#391003
1%
#391503
0%
#392003
b111100 '
1%
b1111 $
b100 !
#392503
0%
#393003
1%
#393503
0%
#394003
1%
#394503
0%
#395003
1%
#395503
0%
#396003
b1111111110111111 '
1%
b101 $
b1111111111110011 !
#396503
0%
#397003
1%
#397503
0%
#398003
1%
#398503
0%
#399003
1%
#399503
0%
#400003
b1111111111110100 '
1%
b11 $
b1111111111111100 !
#400503
0%
#401003
1%
#401503
0%
#402003
1%
#402503
0%
#403003
1%
#403503
0%
#404003
b0 '
1%
b0 $
b1010 !
#404503
0%
#405003
1%
#405503
0%
#406003
1%
#406503
0%
#407003
1%
#407503
0%
#408003
1%
b1101 !
#408503
0%
#409003
1%
#409503
0%
#410003
1%
#410503
0%
#411003
1%
#411503
0%
#412003
b10001111 '
1%
b1101 $
b1011 !
#412503
0%
#413003
1%
#413503
0%
#414003
1%
#414503
0%
#415003
1%
#415503
0%
#416003
b1001011 '
1%
b1111 $
b101 !
#416503
0%
#417003
1%
#417503
0%
#418003
1%
#418503
0%
#419003
1%
#419503
0%
#420003
b1111111111101000 '
1%
b100 $
b1111111111111010 !
#420503
0%
#421003
1%
#421503
0%
#422003
1%
#422503
0%
#423003
1%
#423503
0%
#424003
b1100010 '
1%
b111 $
b1110 !
#424503
0%
#425003
1%
#425503
0%
#426003
1%
#426503
0%
#427003
1%
#427503
0%
#428003
b1111111111000100 '
1%
b1010 $
b1111111111111010 !
#428503
0%
#429003
1%
#429503
0%
#430003
1%
#430503
0%
#431003
1%
#431503
0%
#432003
b1111111111001110 '
1%
b1111111111111011 $
b1010 !
#432503
0%
#433003
1%
#433503
0%
#434003
1%
#434503
0%
#435003
1%
#435503
0%
#436003
b101101 '
1%
b1111111111110001 $
b1111111111111101 !
#436503
0%
#437003
1%
#437503
0%
#438003
1%
#438503
0%
#439003
1%
#439503
0%
#440003
b1111111110111010 '
1%
b1111111111111011 $
b1110 !
#440503
0%
#441003
1%
#441503
0%
#442003
1%
#442503
0%
#443003
1%
#443503
0%
#444003
b1111111111111000 '
1%
b1111111111111100 $
b10 !
#444503
0%
#445003
1%
#445503
0%
#446003
1%
#446503
0%
#447003
1%
#447503
0%
#448003
b110000 '
1%
b1111111111111010 $
b1111111111111000 !
#448503
0%
#449003
1%
#449503
0%
#450003
1%
#450503
0%
#451003
1%
#451503
0%
#452003
b1111111111110101 '
1%
b1011 $
b1111111111111111 !
#452503
0%
#453003
1%
#453503
0%
#454003
1%
#454503
0%
#455003
1%
#455503
0%
#456003
b1111111110110101 '
1%
b101 $
b1111111111110001 !
#456503
0%
#457003
1%
#457503
0%
#458003
1%
#458503
0%
#459003
1%
#459503
0%
#460003
b1111111111101100 '
1%
b1111111111111011 $
b100 !
#460503
0%
#461003
1%
#461503
0%
#462003
1%
#462503
0%
#463003
1%
#463503
0%
#464003
b1111111111111101 '
1%
b11 $
b1111111111111111 !
#464503
0%
#465003
1%
#465503
0%
#466003
1%
#466503
0%
#467003
1%
#467503
0%
#468003
b1111111101010000 '
1%
b1111111111110000 $
b1011 !
#468503
0%
#469003
1%
#469503
0%
#470003
1%
#470503
0%
#471003
1%
#471503
0%
#472003
b1111111110111111 '
1%
b1111111111110011 $
b101 !
#472503
0%
#473003
1%
#473503
0%
#474003
1%
#474503
0%
#475003
1%
#475503
0%
#476003
b0 '
1%
b1111111111111000 $
b0 !
#476503
0%
#477003
1%
#477503
0%
#478003
1%
#478503
0%
#479003
1%
#479503
0%
#480003
b1000110 '
1%
b1110 $
b101 !
#480503
0%
#481003
1%
#481503
0%
#482003
1%
#482503
0%
#483003
1%
#483503
0%
#484003
b1111111110110000 '
1%
b1111111111110000 $
#484503
0%
#485003
1%
#485503
0%
#486003
1%
#486503
0%
#487003
1%
#487503
0%
#488003
b11110000 '
1%
b1111111111110001 $
b1111111111110000 !
#488503
0%
#489003
1%
#489503
0%
#490003
1%
#490503
0%
#491003
1%
#491503
0%
#492003
b1111111111111000 '
1%
b1111111111111110 $
b100 !
#492503
0%
#493003
1%
#493503
0%
#494003
1%
#494503
0%
#495003
1%
#495503
0%
#496003
b1111111111111001 '
1%
b111 $
b1111111111111111 !
#496503
0%
#497003
1%
#497503
0%
#498003
1%
#498503
0%
#499003
1%
#499503
0%
#500003
b1111111110100101 '
1%
b1111111111110011 !
#500503
0%
#501003
1%
#501503
0%
#502003
1%
#502503
0%
#503003
1%
#503503
0%
#504003
b1010 '
1%
b101 $
b10 !
#504503
0%
#505003
1%
#505503
0%
#506003
1%
#506503
0%
#507003
1%
#507503
0%
#508003
b1111111100010000 '
1%
b1111111111110000 $
b1111 !
#508503
0%
#509003
1%
#509503
0%
#510003
1%
#510503
0%
#511003
1%
#511503
0%
#512003
b1111111110101100 '
1%
b1111111111111010 $
b1110 !
#512503
0%
#513003
1%
#513503
0%
#514003
1%
#514503
0%
#515003
1%
#515503
0%
#516003
b1001000 '
1%
b1111111111110111 $
b1111111111111000 !
#516503
0%
#517003
1%
#517503
0%
#518003
1%
#518503
0%
#519003
1%
#519503
0%
#520003
b1111111110011110 '
1%
b1111111111111001 $
b1110 !
#520503
0%
#521003
1%
#521503
0%
#522003
1%
#522503
0%
#523003
1%
#523503
0%
#524003
b11110 '
1%
b1111111111111110 $
b1111111111110001 !
#524503
0%
#525003
1%
#525503
0%
#526003
1%
#526503
0%
#527003
1%
#527503
0%
#528003
b0 '
1%
b0 $
b1111111111110111 !
#528503
0%
#529003
1%
#529503
0%
#530003
1%
#530503
0%
#531003
1%
#531503
0%
#532003
b1111111111110100 '
1%
b1111111111111100 $
b11 !
#532503
0%
#533003
1%
#533503
0%
#534003
1%
#534503
0%
#535003
1%
#535503
0%
#536003
b100011 '
1%
b1111111111111011 $
b1111111111111001 !
#536503
0%
#537003
1%
#537503
0%
#538003
1%
#538503
0%
#539003
1%
#539503
0%
#540003
b10000100 '
1%
b1111111111110100 $
b1111111111110101 !
#540503
0%
#541003
1%
#541503
0%
#542003
1%
#542503
0%
#543003
1%
#543503
0%
#544003
b1110 '
1%
b10 $
b111 !
#544503
0%
#545003
1%
#545503
0%
#546003
1%
#546503
0%
#547003
1%
#547503
0%
#548003
b1100011 '
1%
b1011 $
b1001 !
#548503
0%
#549003
1%
#549503
0%
#550003
1%
#550503
0%
#551003
1%
#551503
0%
#552003
b1111111111111110 '
1%
b10 $
b1111111111111111 !
#552503
0%
#553003
1%
#553503
0%
#554003
1%
#554503
0%
#555003
1%
#555503
0%
#556003
b100000000 '
1%
b1111111111110000 $
b1111111111110000 !
