src/lsu/lsu.v
// ===========================================
// LSU Module for the Compute Unit
// This module handles memory requests for loads and stores. 
// Will follow a rdy/val handshaking protocol to ensure proper data flow.
//
// Load Instruction:
// LW r1 r2 -> Loading the data from memory @ r2 onto r1
// r2 in this case is "rs1" since it is the first source register
// 
// Store Instruction:
// SW r1 r2 -> Store the data on register r1 at memory @ r2
// r1 is "rs2" because it contains our data, and r2 is "rs1" 
//
// Port Overview: 
// 1. mem_ren: read-enable signal, indicating we have a load 
// 2. mem_wen: write_enable signal, indicating we have a write
// 3. rs1: an input containing rs1 register data
// 4. rs2: an input containing rs2 register data
// 5. lsu_out: contains the data of the lsu - only has valid outputs on a load request
// 6. lsu_state: a flag to indicate whether the LSU is ready for more data or not
// ===========================================

module lsu #(
  parameter DATA_ADDR_WIDTH = 8,
            DATA_WIDTH = 16
) (
  input clk,
  input reset, 
  input [3:0] cu_state, 
  input lsu_en,

  // Functional Inputs
  input mem_ren, 
  input mem_wen, 
  input [15:0] rs1, 
  input [15:0] rs2,

  // Functional Outputs
  output [DATA_WIDTH-1:0] lsu_data_out,
  output [1:0] lsu_state, 
  
  // Read (Load) Request
  input read_req_rdy, 
  output [DATA_ADDR_WIDTH-1:0] read_req_addr,
  output read_req_addr_val,
  
  // Read (Load) Response
  output read_resp_rdy,
  input [DATA_WIDTH-1:0] read_resp_data,
  input read_resp_data_val,

  // Write (Store) Request
  input write_req_rdy,
  output [DATA_ADDR_WIDTH-1:0] write_req_addr, 
  output [DATA_WIDTH-1:0] write_req_data, 
  output write_req_val,

  // Write (Store) Response : Only one signal to indicate that we are done writing 
  input write_resp_val 

);

// scheduler localparams
localparam  IDLE = 4'd0, 
            FETCH = 4'd1, 
            DECODE = 4'd2,
            REQ = 4'd3, 
            WAIT = 4'd4,
            EXECUTE = 4'd5, 
            WRITEBACK = 4'd6,
            DONE = 4'd7;

// LSU FSM Parameters
localparam  LSU_IDLE = 2'd0, 
            LSU_REQ  = 2'd1, 
            LSU_WAIT = 2'd2, 
            LSU_DONE = 2'd3; 
   
// LSU FSM Progression:
// IDLE: "default" state, nothing going on and ready to accept a request, only able to move on if the cu state is in request mode
// REQ: Processing the initial request, determining if its load/store, which handshaking signal to activate
// WAIT: Waiting for the memory response after sending a request
// DONE: Finished request, we can progress back to IDLE if our core has completed its action, cu state is in writeback 
reg [1:0] lsu_state_reg; 
assign lsu_state = lsu_state_reg;

// Register-ing Ports to enable assignment on output
reg [DATA_WIDTH-1:0] lsu_data_out_reg;
assign lsu_data_out = lsu_data_out_reg;

reg read_req_addr_val_reg; 
assign read_req_addr_val = read_req_addr_val_reg; 

reg read_resp_rdy_reg; 
assign read_resp_rdy = read_resp_rdy_reg;

reg write_req_val_reg;
assign write_req_val = write_req_val_reg;

reg [DATA_ADDR_WIDTH-1:0] read_req_addr_reg; 
assign read_req_addr = read_req_addr_reg;

reg [DATA_ADDR_WIDTH-1:0] write_req_addr_reg; 
assign write_req_addr = write_req_addr_reg;

reg [DATA_WIDTH-1:0] write_req_data_reg;
assign write_req_data = write_req_data_reg;

// FSM Logic
always @(posedge clk) begin 
  if (reset) begin 
    lsu_data_out_reg <= 0;
    lsu_state_reg <= LSU_IDLE;
    read_req_addr_val_reg <= 0; 
    read_resp_rdy_reg <= 0; 
    write_req_val_reg <= 0;  
  end else begin 
    if (lsu_en) begin 
      if (mem_ren) begin 
        // Load Mode
        case (lsu_state_reg) 

          LSU_IDLE: begin 
            // If we are in data request stage in scheduler, proceed
            if (cu_state == REQ) begin 
              lsu_state_reg <= LSU_REQ; 
            end
          end
          LSU_REQ: begin 
            // Setting read request, if memory is not ready, continue to wait
            if (read_req_rdy) begin 
              read_req_addr_reg <= rs2;
              read_req_addr_val_reg <= 1;
              read_resp_rdy_reg <= 1; // now we are sending out a request, we will be ready to handle response
              lsu_state_reg <= LSU_WAIT;
            end
          end
          LSU_WAIT: begin 
            // Waiting for the read response
            if (read_resp_data_val) begin 
              read_req_addr_val_reg <= 0; // Reset back to 0
              lsu_data_out_reg <= read_resp_data;
              lsu_state_reg <= LSU_DONE; 
              read_resp_rdy_reg <= 0;
            end
          end
          LSU_DONE: begin 
            // Wait for us to go into register writeback
            if (cu_state == WRITEBACK) begin 
              lsu_state_reg <= LSU_IDLE;
            end
          end
          default: lsu_state_reg <= LSU_IDLE;
        endcase
      end
      else if (mem_wen) begin 
        // Store Mode
        case (lsu_state_reg) 
          LSU_IDLE: begin 
            // Waiting for core to go into request mode again 
            if (cu_state == REQ) begin 
              lsu_state_reg <= LSU_REQ;
            end
          end
          LSU_REQ: begin 
            // Need to check if memory is ready to send a memory write request
            if (write_req_rdy) begin 
              write_req_addr_reg <= rs2; 
              write_req_data_reg <= rs1; 
              write_req_val_reg <= 1;
              lsu_state_reg <= LSU_WAIT;
            end
          end
          LSU_WAIT: begin 
            // Waiting for the memory to finish writing 
            if (write_resp_val) begin 
              write_req_val_reg <= 0; 
              lsu_state_reg <= LSU_DONE;
            end
          end
          LSU_DONE: begin 
            if (cu_state == WRITEBACK) begin 
              lsu_state_reg <= LSU_IDLE;
            end
          end
          default: lsu_state_reg <= LSU_IDLE;
        endcase
      end
    end
  end
end


endmodule

wrapper/lsu/wrapper_lsu.v
`include "../../src/lsu/lsu.v"
`timescale 1ns/1ps
module wrapper_lsu #(
  parameter DATA_ADDR_WIDTH = 8,
            DATA_WIDTH = 16
) (
  input clk,
  input reset, 
  input [3:0] cu_state, 
  input lsu_en,

  // Functional Inputs
  input mem_ren, 
  input mem_wen, 
  input [15:0] rs1, 
  input [15:0] rs2,

  // Functional Outputs
  output [DATA_WIDTH-1:0] lsu_data_out,
  output [1:0] lsu_state, 
  
  // Read (Load) Request
  input read_req_rdy, 
  output [DATA_ADDR_WIDTH-1:0] read_req_addr,
  output read_req_addr_val,
  
  // Read (Load) Response
  output read_resp_rdy,
  input [DATA_WIDTH-1:0] read_resp_data,
  input read_resp_data_val,

  // Write (Store) Request
  input write_req_rdy,
  output [DATA_ADDR_WIDTH-1:0] write_req_addr, 
  output [DATA_WIDTH-1:0] write_req_data, 
  output write_req_val,

  // Write (Store) Response : Only one signal to indicate that we are done writing 
  input write_resp_val 
);

lsu #(
  .DATA_ADDR_WIDTH(DATA_ADDR_WIDTH),
  .DATA_WIDTH(DATA_WIDTH)
) inst_lsu(
  .clk(clk),
  .reset(reset),
  .cu_state(cu_state),
  .lsu_en(lsu_en),
  .mem_ren(mem_ren),
  .mem_wen(mem_wen),
  .rs1(rs1),
  .rs2(rs2),
  .lsu_data_out(lsu_data_out),
  .lsu_state(lsu_state),
  .read_req_rdy(read_req_rdy),
  .read_req_addr(read_req_addr),
  .read_req_addr_val(read_req_addr_val),
  .read_resp_rdy(read_resp_rdy),
  .read_resp_data(read_resp_data),
  .read_resp_data_val(read_resp_data_val),
  .write_req_rdy(write_req_rdy),
  .write_req_addr(write_req_addr),
  .write_req_data(write_req_data),
  .write_req_val(write_req_val),
  .write_resp_val(write_resp_val)
);

initial begin 
  $dumpfile("lsu_dump.vcd");
  $dumpvars(1, inst_lsu);
end
endmodule

test/lsu_test/lsu_dump.vcd
$date
	Wed Jan  8 21:57:21 2025
$end
$version
	Icarus Verilog
$end
$timescale
	1ps
$end
$scope module wrapper_lsu $end
$scope module inst_lsu $end
$var wire 1 ! clk $end
$var wire 4 " cu_state [3:0] $end
$var wire 16 # lsu_data_out [15:0] $end
$var wire 1 $ lsu_en $end
$var wire 2 % lsu_state [1:0] $end
$var wire 1 & mem_ren $end
$var wire 1 ' mem_wen $end
$var wire 8 ( read_req_addr [7:0] $end
$var wire 1 ) read_req_addr_val $end
$var wire 1 * read_req_rdy $end
$var wire 16 + read_resp_data [15:0] $end
$var wire 1 , read_resp_data_val $end
$var wire 1 - read_resp_rdy $end
$var wire 1 . reset $end
$var wire 16 / rs1 [15:0] $end
$var wire 16 0 rs2 [15:0] $end
$var wire 8 1 write_req_addr [7:0] $end
$var wire 16 2 write_req_data [15:0] $end
$var wire 1 3 write_req_rdy $end
$var wire 1 4 write_req_val $end
$var wire 1 5 write_resp_val $end
$var parameter 32 6 DATA_ADDR_WIDTH $end
$var parameter 32 7 DATA_WIDTH $end
$var parameter 4 8 DECODE $end
$var parameter 4 9 DONE $end
$var parameter 4 : EXECUTE $end
$var parameter 4 ; FETCH $end
$var parameter 4 < IDLE $end
$var parameter 2 = LSU_DONE $end
$var parameter 2 > LSU_IDLE $end
$var parameter 2 ? LSU_REQ $end
$var parameter 2 @ LSU_WAIT $end
$var parameter 4 A REQ $end
$var parameter 4 B WAIT $end
$var parameter 4 C WRITEBACK $end
$var reg 16 D lsu_data_out_reg [15:0] $end
$var reg 2 E lsu_state_reg [1:0] $end
$var reg 8 F read_req_addr_reg [7:0] $end
$var reg 1 G read_req_addr_val_reg $end
$var reg 1 H read_resp_rdy_reg $end
$var reg 8 I write_req_addr_reg [7:0] $end
$var reg 16 J write_req_data_reg [15:0] $end
$var reg 1 K write_req_val_reg $end
$upscope $end
$upscope $end
$enddefinitions $end
$comment Show the parameter values. $end
$dumpall
b110 C
b100 B
b11 A
b10 @
b1 ?
b0 >
b11 =
b0 <
b1 ;
b101 :
b111 9
b10 8
b10000 7
b1000 6
$end
#0
$dumpvars
xK
bx J
bx I
xH
xG
bx F
bx E
bx D
z5
x4
z3
bx 2
bx 1
bz 0
bz /
0.
x-
z,
bz +
z*
x)
bx (
z'
z&
bx %
1$
bx #
bz "
1!
$end
#500
0!
#1000
04
0K
0-
0H
0)
0G
b0 %
b0 E
b0 #
b0 D
1!
1.
#1500
0!
#2000
1!
0.
#2500
0!
#3000
1!
#3500
0!
#4000
1!
#4500
0!
#5000
1!
#5500
0!
#6000
1!
#6500
0!
#7000
1!
#7500
0!
#8000
1!
#8500
0!
#9000
1!
#9500
0!
#10000
b0 0
b0 /
0'
1&
b11 "
1!
b0 +
05
13
0,
1*
#10500
0!
#11000
b1 %
b1 E
1!
#11500
0!
#12000
b10 %
b10 E
1-
1H
1)
1G
b0 (
b0 F
1!
#12500
0!
#13000
b1111000011110000 +
1,
1!
#13500
0!
#14000
0-
0H
b11 %
b11 E
b1111000011110000 #
b1111000011110000 D
0)
0G
1!
#14500
0!
#15000
b0 +
0,
b110 "
1!
#15500
0!
#16000
b0 %
b0 E
1!
#16500
0!
#17000
b101 0
b1 /
b11 "
1!
#17500
0!
#18000
b1 %
b1 E
1!
#18500
0!
#19000
b10 %
b10 E
1-
1H
1)
1G
b101 (
b101 F
1!
#19500
0!
#20000
b11001100110011 +
1,
1!
#20500
0!
#21000
0-
0H
b11 %
b11 E
b11001100110011 #
b11001100110011 D
0)
0G
1!
#21500
0!
#22000
b0 +
0,
b110 "
1!
#22500
0!
#23000
b0 %
b0 E
1!
#23500
0!
#24000
b1000 0
b111111110000 /
1'
0&
b11 "
1!
#24500
0!
#25000
b1 %
b1 E
1!
#25500
0!
#26000
b10 %
b10 E
14
1K
b111111110000 2
b111111110000 J
b1000 1
b1000 I
1!
#26500
0!
#27000
15
1!
#27500
0!
#28000
b11 %
b11 E
04
0K
1!
#28500
0!
#29000
05
b110 "
1!
#29500
0!
#30000
b0 %
b0 E
1!
#30500
0!
#31000
b1010 0
b1111000000001111 /
b11 "
1!
#31500
0!
#32000
b1 %
b1 E
1!
#32500
0!
#33000
b10 %
b10 E
14
1K
b1111000000001111 2
b1111000000001111 J
b1010 1
b1010 I
1!
#33500
0!
#34000
15
1!
#34500
0!
#35000
b11 %
b11 E
04
0K
1!
#35500
0!
#36000
05
b110 "
1!
#36500
0!
#37000
b0 %
b0 E
1!
#37500
0!
#38000
b10 /
0'
1&
b11 "
1!
#38500
0!
#39000
b1 %
b1 E
1!
#39500
0!
#40000
b10 %
b10 E
1-
1H
1)
1G
b1010 (
b1010 F
1!
#40500
0!
#41000
b1111000000001111 +
1,
1!
#41500
0!
#42000
0-
0H
b11 %
b11 E
b1111000000001111 #
b1111000000001111 D
0)
0G
1!
