src/dispatcher/dispatcher.v
// ===========================================
// Dispatcher Module
//
// A top level module design that will decide
// which compute units to "activate" and will interface
// with "user" inputs. Similar to a scheduler 
// within the compute unit, the dispatcher will organize
// which compute units & how many threads will perform the 
// given operation.
//
// For the logic, we will be using a bit-wide logic. AKA:
// If we have 4 active cores, the width of cu_complete is 4 bits
//
// This dispatcher will operate under the base case assumption which is as follows:
// - All active compute units will operate the same set of PC instructions 
//    for the given number of threads, which is at most 16. 
// - There will be an assumed no branch divergence  
//
// I/O Ports:
// 1. thread_count: total number of active threads; max = 16 b/c of 4 CU
// 2. kernel_start: input signal to indicate the start of kernel execution
// 3. cu_complete: Input Signal to track progress of each core 
// 4. cu_enable: Output signal to enable the active cores
// 5. cu_reset: Output reset signals to reset the active cores
// 6. cu_active_threads: Number of active threads per core
// 7. kernel_complete: Signal to track whether or not the current kernel is completed
// ===========================================

module dispatcher #(
  parameter NUM_CORES = 4
) (
  input clk, 
  input reset,

  // Functional Inputs
  input [4:0] thread_count,
  input kernel_start, 

  // I/O to interact with cores 
  input [NUM_CORES-1:0] cu_complete, 
  output [NUM_CORES-1:0] cu_enable,
  output [NUM_CORES-1:0] cu_reset,
  output [2:0] cu_active_threads [NUM_CORES-1:0], 

  // Functional Outputs
  output kernel_complete

); 

reg [2:0] active_cores;
always @(*) active_cores = (thread_count+3)/4; // Logic that will always round up

// Registering outputs
reg [NUM_CORES-1:0] cu_enable_reg; 
reg [NUM_CORES-1:0] cu_reset_reg;
reg [2:0] cu_active_threads_reg [NUM_CORES-1:0]; 
reg kernel_complete_reg;
assign cu_enable = cu_enable_reg;
assign cu_reset = cu_reset_reg;
assign cu_active_threads[0] = cu_active_threads_reg[0];
assign cu_active_threads[1] = cu_active_threads_reg[1];
assign cu_active_threads[2] = cu_active_threads_reg[2];
assign cu_active_threads[3] = cu_active_threads_reg[3];
assign kernel_complete = kernel_complete_reg;

// Internal registers
reg [4:0] counter;
reg initial_reset;
reg cu_complete_check;
integer j;

always @(posedge clk) begin 
  if (reset) begin 
    cu_enable_reg <= 0;
    cu_reset_reg <= 0;
    kernel_complete_reg <= 0;
    for (j=0;j<NUM_CORES;j=j+1) begin 
      cu_active_threads_reg[j] <= 3'b0;
    end
    // Resetting our internals
    counter <= 0;
    initial_reset <= 0;
    cu_complete_check <= 0;
  end else begin 
    if (kernel_start) begin 
      counter <= 0;
      // Need to first reset each core
      if (!initial_reset) begin 
        initial_reset <= 1;
        for (j=0;j<active_cores;j=j+1) begin 
          cu_reset_reg[j] <= 1;
        end
      end
      else begin 
        // Set the reset signals to low; In theory its only high for 1 cycle
        for (j=0;j<active_cores;j=j+1) begin 
          cu_reset_reg[j] <= 0;
        end

        // Enable all active registers
        for (j=0;j<active_cores;j=j+1) begin 
          // Computing the number of active threads per core
          if (counter + 4 > thread_count) begin 
            cu_active_threads_reg[j] <= (thread_count - counter);
          end else begin 
            cu_active_threads_reg[j] <= 4;
            counter = counter + 4;
          end
          // Enabling all of the proper active cores
          cu_enable_reg[j] = 1;
          if (cu_complete[j] && cu_enable_reg[j]) begin 
            cu_enable_reg[j] = 0;
          end
        end

        // Check for completion
        cu_complete_check = 0;
        for (j=0;j<active_cores;j=j+1) begin 
          if (!cu_complete[j] && cu_enable_reg[j]) begin 
            cu_complete_check = 1;
          end
        end
        kernel_complete_reg <= !cu_complete_check;

        // if (!cu_complete_check) begin 
        //   // All cores are complete
        //   kernel_complete_reg <= 1;
        // end else begin 
        //   // Assigning each active core the number of active threads
        //   for (j=0;j<active_cores;j=j+1) begin 
        //     if (counter + 4 > thread_count) begin 
        //       cu_active_threads_reg[j] <= (thread_count - counter);
        //     end else begin 
        //       cu_active_threads_reg[j] <= 4;
        //       counter = counter + 4;
        //     end
        //     // Enabling all of the cores that are not finished)
        //     cu_enable_reg[j] <= 1;
        //     if (cu_complete[j] && cu_enable_reg[j]) begin 
        //       cu_enable_reg[j] <= 0;
        //     end
        //   end
        // end
      end
    end
  end
end

// Helper for dumping wires
wire [2:0] active_thread0; 
wire [2:0] active_thread1; 
wire [2:0] active_thread2; 
wire [2:0] active_thread3;
assign active_thread0 = cu_active_threads[0]; 
assign active_thread1 = cu_active_threads[1]; 
assign active_thread2 = cu_active_threads[2]; 
assign active_thread3 = cu_active_threads[3]; 

endmodule

wrapper/dispatcher/wrapper_dispatcher.v
`include "../../src/dispatcher/dispatcher.v"
module wrapper_dispatcher #(
  parameter NUM_CORES = 4
) (
input clk, 
input reset,

// Functional Inputs
input [4:0] thread_count,
input kernel_start, 

// I/O to interact with cores 
input [NUM_CORES-1:0] cu_complete, 
output [NUM_CORES-1:0] cu_enable,
output [NUM_CORES-1:0] cu_reset,
output [2:0] cu_active_threads [NUM_CORES-1:0], 

// Functional Outputs
output kernel_complete
); 

dispatcher #(
  .NUM_CORES(NUM_CORES)
) inst_dispatcher (
  .clk(clk),
  .reset(reset),
  .thread_count(thread_count),
  .kernel_start(kernel_start),
  .cu_complete(cu_complete),
  .cu_enable(cu_enable),
  .cu_reset(cu_reset),
  .cu_active_threads(cu_active_threads),
  .kernel_complete(kernel_complete)
);

initial begin 
  $dumpfile("dispatcher_dump.vcd");
  $dumpvars(0, inst_dispatcher);
end

endmodule

test/dispatcher_test/dispatcher_dump.vcd
$date
	Sat Jan 11 12:13:52 2025
$end
$version
	Icarus Verilog
$end
$timescale
	1ps
$end
$scope module wrapper_dispatcher $end
$scope module inst_dispatcher $end
$var wire 3 ! active_thread0 [2:0] $end
$var wire 3 " active_thread1 [2:0] $end
$var wire 3 # active_thread2 [2:0] $end
$var wire 3 $ active_thread3 [2:0] $end
$var wire 1 % clk $end
$var wire 4 & cu_complete [3:0] $end
$var wire 4 ' cu_enable [3:0] $end
$var wire 4 ( cu_reset [3:0] $end
$var wire 1 ) kernel_complete $end
$var wire 1 * kernel_start $end
$var wire 1 + reset $end
$var wire 5 , thread_count [4:0] $end
$var parameter 32 - NUM_CORES $end
$var reg 3 . active_cores [2:0] $end
$var reg 5 / counter [4:0] $end
$var reg 1 0 cu_complete_check $end
$var reg 4 1 cu_enable_reg [3:0] $end
$var reg 4 2 cu_reset_reg [3:0] $end
$var reg 1 3 initial_reset $end
$var reg 1 4 kernel_complete_reg $end
$var integer 32 5 j [31:0] $end
$upscope $end
$upscope $end
$enddefinitions $end
$comment Show the parameter values. $end
$dumpall
b100 -
$end
#0
$dumpvars
bx 5
x4
x3
bx 2
bx 1
x0
bx /
b10 .
b1000 ,
0+
z*
x)
bx (
bx '
b0 &
1%
bx $
bx #
bx "
bx !
$end
#500
0%
#1000
00
03
b0 /
b0 $
b0 #
b0 "
b0 !
0)
04
b0 (
b0 2
b0 '
b0 1
b100 5
1%
1+
#1500
0%
#2000
1%
0+
#2500
0%
#3000
1%
#3500
0%
#4000
b11 (
b11 2
13
b10 5
1%
1*
#4500
0%
#5000
b100 "
b100 !
b0 (
b0 2
10
b11 '
b11 1
b0 /
b10 5
1%
#5500
0%
#6000
10
b0 /
b10 5
1%
#6500
0%
#7000
b1 &
10
b0 /
b10 5
1%
#7500
0%
#8000
10
b10 '
b10 1
b0 /
b10 5
1%
#8500
0%
#9000
10
b10 '
b10 1
b0 /
b10 5
1%
#9500
0%
#10000
10
b10 '
b10 1
b0 /
b10 5
1%
#10500
0%
#11000
b11 &
10
b10 '
b10 1
b0 /
b10 5
1%
#11500
0%
#12000
1)
14
00
b0 '
b0 1
b0 /
b10 5
1%
#12500
0%
#13000
b0 '
b0 1
b0 /
b10 5
1%
#13500
0%
#14000
b0 '
b0 1
b0 /
b10 5
1%
#14500
0%
#15000
b0 '
b0 1
b0 /
b10 5
1%
#15500
0%
#16000
b0 '
b0 1
b0 /
b10 5
1%
#16500
0%
#17000
b0 '
b0 1
b0 /
b10 5
1%
#17500
0%
#18000
b0 '
b0 1
b0 /
b10 5
1%
#18500
0%
#19000
b0 '
b0 1
b0 /
b10 5
1%
#19500
0%
#20000
b0 '
b0 1
b0 /
b10 5
1%
#20500
0%
#21000
b0 '
b0 1
b0 /
b10 5
1%
#21500
0%
#22000
b0 '
b0 1
b0 /
b10 5
1%
#22500
0%
#23000
b0 '
b0 1
b0 /
b10 5
1%
