src/controllers/data_control.v
// ===========================================
// Data Memory Controller
// 
// Memory controller to handle requests from the LSU
// To simply things, it processes requests from a single 
// core at a time, essentially supporting a 4-wide data req/resp
// instead of supporting 4 unqiue threads.
// 
// ===========================================
module data_controller #(
  parameter NUM_DATA_CHAN = 1, 
            NUM_CORES = 4,
            MEM_ADDR_WIDTH = 8,
            MEM_DATA_WIDTH = 16,
            MAX_THREADS = 4
) (
  input clk,
  input reset,
  // I/O With Compute Units
  // LSU Read Request
  output read_req_rdy                         [(NUM_CORES * MAX_THREADS)-1:0], 
  input [MEM_ADDR_WIDTH-1:0] read_req_addr    [(NUM_CORES * MAX_THREADS)-1:0],
  input read_req_addr_val                     [(NUM_CORES * MAX_THREADS)-1:0],
  // LSU Read Response
  input read_resp_rdy                         [(NUM_CORES * MAX_THREADS)-1:0],
  output [MEM_DATA_WIDTH-1:0] read_resp_data  [(NUM_CORES * MAX_THREADS)-1:0],
  output read_resp_data_val                   [(NUM_CORES * MAX_THREADS)-1:0],
  // Write Request
  output write_req_rdy                        [(NUM_CORES * MAX_THREADS)-1:0],
  input [MEM_ADDR_WIDTH-1:0] write_req_addr   [(NUM_CORES * MAX_THREADS)-1:0],
  input [MEM_DATA_WIDTH-1:0] write_req_data   [(NUM_CORES * MAX_THREADS)-1:0],
  input write_req_val                         [(NUM_CORES * MAX_THREADS)-1:0],
  // Write Response
  output write_resp_val                       [(NUM_CORES * MAX_THREADS)-1:0],

  // I/O With Global Memory
  // Memory Access Signals - LSU
  input mem2read_req_rdy                        [MAX_THREADS-1:0], 
  output [MEM_ADDR_WIDTH-1:0] mem2read_req_addr [MAX_THREADS-1:0],
  output mem2read_req_addr_val                  [MAX_THREADS-1:0],
  
  // Read (Load) Response
  output mem2read_resp_rdy                      [MAX_THREADS-1:0],
  input [MEM_DATA_WIDTH-1:0] mem2read_resp_data [MAX_THREADS-1:0],
  input mem2read_resp_data_val                  [MAX_THREADS-1:0],

  // Write (Store) Request
  input mem2write_req_rdy                         [MAX_THREADS-1:0],
  output [MEM_ADDR_WIDTH-1:0] mem2write_req_addr  [MAX_THREADS-1:0], 
  output [MEM_DATA_WIDTH-1:0] mem2write_req_data  [MAX_THREADS-1:0], 
  output mem2write_req_val                        [MAX_THREADS-1:0],

  // Write Response
  input mem2write_resp_val                        [MAX_THREADS-1:0],

  // Functional I/O (For TB)
  input [3:0] compute_state [NUM_CORES-1:0],
  // For debugging
  output [NUM_CORES-1:0] compute_unit

);

localparam  REQ = 4'd3, 
            WAIT = 4'd4,
            EXECUTE = 4'd5, 
            WRITEBACK = 4'd6,
            DONE = 4'd7;

// Progression localparam
localparam  IDLE = 4'd0,      // Channel is waiting for a memory request
            READ_REQUEST = 4'd1,   // Channel is processing the mem req
            RESPONSE = 4'd2,  // Channel is sending mem resp to appropriate compute unit
            WRITE_REQUEST = 4'd3;
// Registering Outputs
reg read_req_rdy_reg                        [(NUM_CORES * MAX_THREADS)-1:0];
reg [MEM_DATA_WIDTH-1:0] read_resp_data_reg [(NUM_CORES * MAX_THREADS)-1:0];
reg read_resp_data_val_reg                  [(NUM_CORES * MAX_THREADS)-1:0];
reg write_req_rdy_reg                       [(NUM_CORES * MAX_THREADS)-1:0];
reg write_resp_val_reg                      [(NUM_CORES * MAX_THREADS)-1:0];
reg [MEM_ADDR_WIDTH-1:0] mem2read_req_addr_reg  [MAX_THREADS-1:0];
reg mem2read_req_addr_val_reg                   [MAX_THREADS-1:0];
reg mem2read_resp_rdy_reg                       [MAX_THREADS-1:0];
reg [MEM_ADDR_WIDTH-1:0] mem2write_req_addr_reg [MAX_THREADS-1:0];
reg [MEM_DATA_WIDTH-1:0] mem2write_req_data_reg [MAX_THREADS-1:0];
reg mem2write_req_val_reg                       [MAX_THREADS-1:0];

genvar j;
for (j=0;j<NUM_CORES*MAX_THREADS;j=j+1) begin 
  assign read_req_rdy[j] = read_req_rdy_reg[j];
  // assign read_req_rdy[j] = mem2read_req_rdy[j];
  assign read_resp_data[j] = read_resp_data_reg[j];
  assign read_resp_data_val[j] = read_resp_data_val_reg[j];
  assign write_req_rdy[j] = write_req_rdy_reg[j];
  assign write_resp_val[j] = write_resp_val_reg[j];
end
for (j=0;j<MAX_THREADS;j=j+1) begin 
  assign mem2read_req_addr[j] = mem2read_req_addr_reg[j];
  assign mem2read_req_addr_val[j] = mem2read_req_addr_val_reg[j];
  assign mem2read_resp_rdy[j] = mem2read_resp_rdy_reg[j];
  assign mem2write_req_addr[j] = mem2write_req_addr_reg[j];
  assign mem2write_req_data[j] = mem2write_req_data_reg[j];
  assign mem2write_req_val[j] = mem2write_req_val_reg[j];
end

wire [3:0] is_read_ready [NUM_CORES-1:0]; 
wire [3:0] is_write_ready [NUM_CORES-1:0];
for (j=0;j<MAX_THREADS*NUM_CORES;j=j+1) begin 
  if (j == 3) begin 
    assign is_read_ready[0][0] = read_req_addr_val[0];
    assign is_read_ready[0][1] = read_req_addr_val[1];
    assign is_read_ready[0][2] = read_req_addr_val[2];
    assign is_read_ready[0][3] = read_req_addr_val[3];
    assign is_write_ready[0][0] = write_req_val[0];
    assign is_write_ready[0][1] = write_req_val[1];
    assign is_write_ready[0][2] = write_req_val[2];
    assign is_write_ready[0][3] = write_req_val[3];
  end else if (j == 7) begin 
    assign is_read_ready[1][0] = read_req_addr_val[4];
    assign is_read_ready[1][1] = read_req_addr_val[5];
    assign is_read_ready[1][2] = read_req_addr_val[6];
    assign is_read_ready[1][3] = read_req_addr_val[7];
    assign is_write_ready[1][0] = write_req_val[4];
    assign is_write_ready[1][1] = write_req_val[5];
    assign is_write_ready[1][2] = write_req_val[6];
    assign is_write_ready[1][3] = write_req_val[7];
  end else if (j == 11) begin 
    assign is_read_ready[2][0] = read_req_addr_val[8];
    assign is_read_ready[2][1] = read_req_addr_val[9];
    assign is_read_ready[2][2] = read_req_addr_val[10];
    assign is_read_ready[2][3] = read_req_addr_val[11];
    assign is_write_ready[2][0] = write_req_val[8];
    assign is_write_ready[2][1] = write_req_val[9];
    assign is_write_ready[2][2] = write_req_val[10];
    assign is_write_ready[2][3] = write_req_val[11];
  end else if (j == 15) begin 
    assign is_read_ready[3][0] = read_req_addr_val[12];
    assign is_read_ready[3][1] = read_req_addr_val[13];
    assign is_read_ready[3][2] = read_req_addr_val[14];
    assign is_read_ready[3][3] = read_req_addr_val[15];
    assign is_write_ready[3][0] = write_req_val[12];
    assign is_write_ready[3][1] = write_req_val[13];
    assign is_write_ready[3][2] = write_req_val[14];
    assign is_write_ready[3][3] = write_req_val[15];
  end
end

for (j=0;j<MAX_THREADS*NUM_CORES;j=j+1) begin 
  if (j < 4) begin 
    assign read_req_rdy_reg[j] = mem2read_req_rdy[0];
    assign write_req_rdy_reg[j] = mem2write_req_rdy[0];
  end else if (j < 8) begin 
    assign read_req_rdy_reg[j] = mem2read_req_rdy[1];
    assign write_req_rdy_reg[j] = mem2write_req_rdy[1];
  end else if (j < 12) begin 
    assign read_req_rdy_reg[j] = mem2read_req_rdy[2]; 
    assign write_req_rdy_reg[j] = mem2write_req_rdy[2];
  end else if (j < 16) begin 
    assign read_req_rdy_reg[j] = mem2read_req_rdy[3]; 
    assign write_req_rdy_reg[j] = mem2write_req_rdy[3];
  end
end

// Internal states
reg [3:0] channel_state;
reg [NUM_CORES-1:0] selected_unit;
assign compute_unit = selected_unit;

integer i;
always @(posedge clk) begin 
  if (reset) begin 
      // read_req_rdy_reg[i] <= 0;
      // read_req_rdy_reg[i] <= mem2read_req_rdy[mem_chan];
      read_resp_data_reg[i] <= 0;
      read_resp_data_val_reg[i] <= 0;
      // write_req_rdy_reg[i] <= mem2write_req_rdy[mem_chan];
      write_resp_val_reg[i] <= 0;
    for (i=0;i<MAX_THREADS;i=i+1)begin 
      mem2read_req_addr_reg[i] <= 0;
      mem2read_req_addr_val_reg[i] <= 0;
      mem2read_resp_rdy_reg[i] <= 0;
      mem2write_req_addr_reg[i] <= 0;
      mem2write_req_data_reg[i] <= 0;
      mem2write_req_val_reg[i] <= 0;
    end
    channel_state <= IDLE;
    selected_unit <= 0;
  end else begin 
    case (channel_state)
      IDLE: begin 
        // Iterate through the active cores to find one with all 4 channels ready 
        for (i=0;i<NUM_CORES;i=i+1)begin 
          // First Conducting read request check 
          if (is_read_ready[i] == 15) begin 
            selected_unit <= i;
            channel_state <= READ_REQUEST;
            i = NUM_CORES-1;
          end
          // Also conduct a write check
          if (is_write_ready[i] == 15) begin 
            selected_unit <= i;
            channel_state <= WRITE_REQUEST;
            i = NUM_CORES-1;
          end
        end
      end
      READ_REQUEST: begin 
        // Pass through the values
        for (i=0;i<MAX_THREADS;i=i+1) begin 
          mem2read_req_addr_val_reg[i] <= read_req_addr_val[4*selected_unit+i];
          mem2read_req_addr_reg[i] <= read_req_addr[4*selected_unit+i];
          mem2read_resp_rdy_reg[i] <= read_resp_rdy[4*selected_unit+i];
          if (mem2read_resp_data_val[i] && read_resp_rdy[4*selected_unit+i]) begin 
            read_resp_data_reg[4*selected_unit+i] <= mem2read_resp_data[i];
            read_resp_data_val_reg[4*selected_unit+i] <= mem2read_resp_data_val[i];
            channel_state <= RESPONSE;
          end
        end
      end
      WRITE_REQUEST: begin 
        for (i=0;i<MAX_THREADS;i=i+1) begin 
          mem2write_req_addr_reg[i] <= write_req_addr[4*selected_unit+i];
          mem2write_req_data_reg[i] <= write_req_data[4*selected_unit+i];
          mem2write_req_val_reg[i] <= write_req_val[4*selected_unit+i];
          if (mem2write_resp_val[i]) begin
            write_resp_val_reg[4*selected_unit+i] <= mem2write_resp_val[i]; // !!! Not sure if we even use this signal
            channel_state <= RESPONSE;
          end
        end
      end
      RESPONSE: begin 
        // Reset values if we have finished accepting the request
        if (compute_state[selected_unit] == WRITEBACK) begin
          for (i=0;i<MAX_THREADS;i=i+1) begin 
            // Resetting Read Signals
            mem2read_req_addr_val_reg[i] <= 0;
            mem2read_req_addr_reg[i] <= 0;
            mem2read_resp_rdy_reg[i] <= 0;
            read_resp_data_reg[4*selected_unit+i] <= 0;
            read_resp_data_val_reg[4*selected_unit+i] <= 0;

            // Resetting Write Signals
            mem2write_req_addr_reg[i] <= 0;
            mem2write_req_data_reg[i] <= 0;
            mem2write_req_val_reg[i] <= 0;
            write_resp_val_reg[4*selected_unit+i] <= 0;
            channel_state <= IDLE;
            selected_unit <= 0;
          end
        end
      end
    endcase
  end
end

// Debugging wires
wire read_req_rdy0;
wire mem2read_req_rdy0;
assign read_req_rdy0 = read_req_rdy_reg[0];
assign mem2read_req_rdy0 = mem2read_req_rdy[0];




endmodule

wrapper/controller/wrapper_datacont.v
`include "../../src/controllers/data_control.v"
module wrapper_datacontroller #(
  parameter NUM_DATA_CHAN = 1, 
            NUM_CORES = 4,
            MEM_ADDR_WIDTH = 8,
            MEM_DATA_WIDTH = 16,
            MAX_THREADS = 4
) (
  input clk,
  input reset,
  // I/O With Compute Units
  // LSU Read Request
  output read_req_rdy                         [(NUM_CORES * MAX_THREADS)-1:0], 
  input [MEM_ADDR_WIDTH-1:0] read_req_addr    [(NUM_CORES * MAX_THREADS)-1:0],
  input read_req_addr_val                     [(NUM_CORES * MAX_THREADS)-1:0],
  // LSU Read Response
  input read_resp_rdy                         [(NUM_CORES * MAX_THREADS)-1:0],
  output [MEM_DATA_WIDTH-1:0] read_resp_data  [(NUM_CORES * MAX_THREADS)-1:0],
  output read_resp_data_val                   [(NUM_CORES * MAX_THREADS)-1:0],
  // Write Request
  output write_req_rdy                        [(NUM_CORES * MAX_THREADS)-1:0],
  input [MEM_ADDR_WIDTH-1:0] write_req_addr   [(NUM_CORES * MAX_THREADS)-1:0],
  input [MEM_DATA_WIDTH-1:0] write_req_data   [(NUM_CORES * MAX_THREADS)-1:0],
  input write_req_val                         [(NUM_CORES * MAX_THREADS)-1:0],
  // Write Response
  output write_resp_val                       [(NUM_CORES * MAX_THREADS)-1:0],

  // I/O With Global Memory
  // Memory Access Signals - LSU
  input mem2read_req_rdy                        [MAX_THREADS-1:0], 
  output [MEM_ADDR_WIDTH-1:0] mem2read_req_addr [MAX_THREADS-1:0],
  output mem2read_req_addr_val                  [MAX_THREADS-1:0],
  
  // Read (Load) Response
  output mem2read_resp_rdy                      [MAX_THREADS-1:0],
  input [MEM_DATA_WIDTH-1:0] mem2read_resp_data [MAX_THREADS-1:0],
  input mem2read_resp_data_val                  [MAX_THREADS-1:0],

  // Write (Store) Request
  input mem2write_req_rdy                         [MAX_THREADS-1:0],
  output [MEM_ADDR_WIDTH-1:0] mem2write_req_addr  [MAX_THREADS-1:0], 
  output [MEM_DATA_WIDTH-1:0] mem2write_req_data  [MAX_THREADS-1:0], 
  output mem2write_req_val                        [MAX_THREADS-1:0],

  // Write Response
  input mem2write_resp_val                        [MAX_THREADS-1:0],

  // Functional I/O (For TB)
  input [3:0] compute_state [NUM_CORES-1:0],
  // For debugging
  output [NUM_CORES-1:0] compute_unit
);

data_controller #(
  .NUM_DATA_CHAN(NUM_DATA_CHAN),
  .NUM_CORES(NUM_CORES),
  .MEM_ADDR_WIDTH(MEM_ADDR_WIDTH),
  .MEM_DATA_WIDTH(MEM_DATA_WIDTH),
  .MAX_THREADS(MAX_THREADS)
) inst_datacont (
  .clk(clk),
  .reset(reset),
  .read_req_rdy(read_req_rdy),
  .read_req_addr(read_req_addr),
  .read_req_addr_val(read_req_addr_val),
  .read_resp_rdy(read_resp_rdy),
  .read_resp_data(read_resp_data),
  .read_resp_data_val(read_resp_data_val),
  .write_req_rdy(write_req_rdy),
  .write_req_addr(write_req_addr),
  .write_req_data(write_req_data),
  .write_req_val(write_req_val),
  .write_resp_val(write_resp_val),
  .mem2read_req_rdy(mem2read_req_rdy),
  .mem2read_req_addr(mem2read_req_addr),
  .mem2read_req_addr_val(mem2read_req_addr_val),
  .mem2read_resp_rdy(mem2read_resp_rdy),
  .mem2read_resp_data(mem2read_resp_data),
  .mem2read_resp_data_val(mem2read_resp_data_val),
  .mem2write_req_rdy(mem2write_req_rdy),
  .mem2write_req_addr(mem2write_req_addr),
  .mem2write_req_data(mem2write_req_data),
  .mem2write_req_val(mem2write_req_val),
  .mem2write_resp_val(mem2write_resp_val),
  .compute_state(compute_state),
  .compute_unit(compute_unit)
);

// Dump
initial begin 
  $dumpfile("datacont_dump.vcd");
  $dumpvars(0, inst_datacont);
end

endmodule

test/datacontrol_test/datacont_dump.vcd
$date
	Mon Jan 13 17:00:57 2025
$end
$version
	Icarus Verilog
$end
$timescale
	1ps
$end
$scope module wrapper_datacontroller $end
$scope module inst_datacont $end
$var wire 1 ! clk $end
$var wire 4 " compute_unit [3:0] $end
$var wire 1 # mem2read_req_rdy0 $end
$var wire 1 $ read_req_rdy0 $end
$var wire 1 % reset $end
$var parameter 4 & DONE $end
$var parameter 4 ' EXECUTE $end
$var parameter 4 ( IDLE $end
$var parameter 32 ) MAX_THREADS $end
$var parameter 32 * MEM_ADDR_WIDTH $end
$var parameter 32 + MEM_DATA_WIDTH $end
$var parameter 32 , NUM_CORES $end
$var parameter 32 - NUM_DATA_CHAN $end
$var parameter 4 . READ_REQUEST $end
$var parameter 4 / REQ $end
$var parameter 4 0 RESPONSE $end
$var parameter 4 1 WAIT $end
$var parameter 4 2 WRITEBACK $end
$var parameter 4 3 WRITE_REQUEST $end
$var reg 4 4 channel_state [3:0] $end
$var reg 4 5 selected_unit [3:0] $end
$var integer 32 6 i [31:0] $end
$scope begin genblk1[0] $end
$var parameter 2 7 j $end
$upscope $end
$scope begin genblk1[1] $end
$var parameter 2 8 j $end
$upscope $end
$scope begin genblk1[2] $end
$var parameter 3 9 j $end
$upscope $end
$scope begin genblk1[3] $end
$var parameter 3 : j $end
$upscope $end
$scope begin genblk1[4] $end
$var parameter 4 ; j $end
$upscope $end
$scope begin genblk1[5] $end
$var parameter 4 < j $end
$upscope $end
$scope begin genblk1[6] $end
$var parameter 4 = j $end
$upscope $end
$scope begin genblk1[7] $end
$var parameter 4 > j $end
$upscope $end
$scope begin genblk1[8] $end
$var parameter 5 ? j $end
$upscope $end
$scope begin genblk1[9] $end
$var parameter 5 @ j $end
$upscope $end
$scope begin genblk1[10] $end
$var parameter 5 A j $end
$upscope $end
$scope begin genblk1[11] $end
$var parameter 5 B j $end
$upscope $end
$scope begin genblk1[12] $end
$var parameter 5 C j $end
$upscope $end
$scope begin genblk1[13] $end
$var parameter 5 D j $end
$upscope $end
$scope begin genblk1[14] $end
$var parameter 5 E j $end
$upscope $end
$scope begin genblk1[15] $end
$var parameter 5 F j $end
$upscope $end
$scope begin genblk2[0] $end
$var parameter 2 G j $end
$upscope $end
$scope begin genblk2[1] $end
$var parameter 2 H j $end
$upscope $end
$scope begin genblk2[2] $end
$var parameter 3 I j $end
$upscope $end
$scope begin genblk2[3] $end
$var parameter 3 J j $end
$upscope $end
$scope begin genblk3[0] $end
$var parameter 2 K j $end
$upscope $end
$scope begin genblk3[1] $end
$var parameter 2 L j $end
$upscope $end
$scope begin genblk3[2] $end
$var parameter 3 M j $end
$upscope $end
$scope begin genblk3[3] $end
$var parameter 3 N j $end
$scope begin genblk1 $end
$upscope $end
$upscope $end
$scope begin genblk3[4] $end
$var parameter 4 O j $end
$upscope $end
$scope begin genblk3[5] $end
$var parameter 4 P j $end
$upscope $end
$scope begin genblk3[6] $end
$var parameter 4 Q j $end
$upscope $end
$scope begin genblk3[7] $end
$var parameter 4 R j $end
$scope begin genblk1 $end
$upscope $end
$upscope $end
$scope begin genblk3[8] $end
$var parameter 5 S j $end
$upscope $end
$scope begin genblk3[9] $end
$var parameter 5 T j $end
$upscope $end
$scope begin genblk3[10] $end
$var parameter 5 U j $end
$upscope $end
$scope begin genblk3[11] $end
$var parameter 5 V j $end
$scope begin genblk1 $end
$upscope $end
$upscope $end
$scope begin genblk3[12] $end
$var parameter 5 W j $end
$upscope $end
$scope begin genblk3[13] $end
$var parameter 5 X j $end
$upscope $end
$scope begin genblk3[14] $end
$var parameter 5 Y j $end
$upscope $end
$scope begin genblk3[15] $end
$var parameter 5 Z j $end
$scope begin genblk1 $end
$upscope $end
$upscope $end
$scope begin genblk4[0] $end
$var parameter 2 [ j $end
$scope begin genblk1 $end
$upscope $end
$upscope $end
$scope begin genblk4[1] $end
$var parameter 2 \ j $end
$scope begin genblk1 $end
$upscope $end
$upscope $end
$scope begin genblk4[2] $end
$var parameter 3 ] j $end
$scope begin genblk1 $end
$upscope $end
$upscope $end
$scope begin genblk4[3] $end
$var parameter 3 ^ j $end
$scope begin genblk1 $end
$upscope $end
$upscope $end
$scope begin genblk4[4] $end
$var parameter 4 _ j $end
$scope begin genblk1 $end
$upscope $end
$upscope $end
$scope begin genblk4[5] $end
$var parameter 4 ` j $end
$scope begin genblk1 $end
$upscope $end
$upscope $end
$scope begin genblk4[6] $end
$var parameter 4 a j $end
$scope begin genblk1 $end
$upscope $end
$upscope $end
$scope begin genblk4[7] $end
$var parameter 4 b j $end
$scope begin genblk1 $end
$upscope $end
$upscope $end
$scope begin genblk4[8] $end
$var parameter 5 c j $end
$scope begin genblk1 $end
$upscope $end
$upscope $end
$scope begin genblk4[9] $end
$var parameter 5 d j $end
$scope begin genblk1 $end
$upscope $end
$upscope $end
$scope begin genblk4[10] $end
$var parameter 5 e j $end
$scope begin genblk1 $end
$upscope $end
$upscope $end
$scope begin genblk4[11] $end
$var parameter 5 f j $end
$scope begin genblk1 $end
$upscope $end
$upscope $end
$scope begin genblk4[12] $end
$var parameter 5 g j $end
$scope begin genblk1 $end
$upscope $end
$upscope $end
$scope begin genblk4[13] $end
$var parameter 5 h j $end
$scope begin genblk1 $end
$upscope $end
$upscope $end
$scope begin genblk4[14] $end
$var parameter 5 i j $end
$scope begin genblk1 $end
$upscope $end
$upscope $end
$scope begin genblk4[15] $end
$var parameter 5 j j $end
$scope begin genblk1 $end
$upscope $end
$upscope $end
$upscope $end
$upscope $end
$enddefinitions $end
$comment Show the parameter values. $end
$dumpall
b1111 j
b1110 i
b1101 h
b1100 g
b1011 f
b1010 e
b1001 d
b1000 c
b111 b
b110 a
b101 `
b100 _
b11 ^
b10 ]
b1 \
b0 [
b1111 Z
b1110 Y
b1101 X
b1100 W
b1011 V
b1010 U
b1001 T
b1000 S
b111 R
b110 Q
b101 P
b100 O
b11 N
b10 M
b1 L
b0 K
b11 J
b10 I
b1 H
b0 G
b1111 F
b1110 E
b1101 D
b1100 C
b1011 B
b1010 A
b1001 @
b1000 ?
b111 >
b110 =
b101 <
b100 ;
b11 :
b10 9
b1 8
b0 7
b11 3
b110 2
b100 1
b10 0
b11 /
b1 .
b1 -
b100 ,
b10000 +
b1000 *
b100 )
b0 (
b101 '
b111 &
$end
#0
$dumpvars
bx 6
bx 5
bx 4
0%
z$
z#
bx "
1!
$end
#500
0!
#1000
b0 "
b0 5
b0 4
b100 6
1!
1%
#1500
0!
#2000
b100 6
1!
0%
#2500
0!
#3000
b100 6
1!
#3500
0!
#4000
b100 6
1!
#4500
0!
#5000
b100 6
1!
#5500
0!
#6000
b100 6
1!
#6500
0!
#7000
b100 6
1!
#7500
0!
#8000
b100 6
1!
#8500
0!
#9000
b100 6
1!
#9500
0!
#10000
b100 6
1!
1#
1$
#10500
0!
#11000
b11 4
b100 6
1!
#11500
0!
#12000
b100 6
1!
#12500
0!
#13000
b100 6
1!
#13500
0!
#14000
b10 4
b100 6
1!
#14500
0!
#15000
1!
#15500
0!
#16000
b0 4
b100 6
1!
#16500
0!
#17000
b11 4
b1 "
b1 5
b100 6
1!
#17500
0!
#18000
b100 6
1!
#18500
0!
#19000
b100 6
1!
#19500
0!
#20000
b10 4
b100 6
1!
#20500
0!
#21000
1!
#21500
0!
#22000
b0 "
b0 5
b0 4
b100 6
1!
#22500
0!
#23000
b11 4
b10 "
b10 5
b100 6
1!
#23500
0!
#24000
b100 6
1!
#24500
0!
#25000
b100 6
1!
#25500
0!
#26000
b10 4
b100 6
1!
#26500
0!
#27000
1!
#27500
0!
#28000
b0 "
b0 5
b0 4
b100 6
1!
#28500
0!
#29000
b11 4
b11 "
b11 5
b100 6
1!
#29500
0!
#30000
b100 6
1!
#30500
0!
#31000
b100 6
1!
#31500
0!
#32000
b10 4
b100 6
1!
#32500
0!
#33000
1!
#33500
0!
#34000
b0 "
b0 5
b0 4
b100 6
1!
#34500
0!
#35000
b100 6
1!
#35500
0!
#36000
b100 6
1!
#36500
0!
#37000
b100 6
1!
#37500
0!
#38000
b100 6
1!
#38500
0!
#39000
b100 6
1!
#39500
0!
#40000
b100 6
1!
#40500
0!
#41000
b100 6
1!
#41500
0!
#42000
b100 6
1!
#42500
0!
#43000
b100 6
1!
#43500
0!
#44000
b100 6
1!
#44500
0!
#45000
b100 6
1!
#45500
0!
#46000
b100 6
1!
#46500
0!
#47000
b100 6
1!
#47500
0!
#48000
b100 6
1!
#48500
0!
#49000
b100 6
1!
#49500
0!
#50000
b100 6
1!
#50500
0!
#51000
b100 6
1!
#51500
0!
#52000
b100 6
1!
#52500
0!
#53000
b100 6
1!
#53500
0!
#54000
b100 6
1!
#54500
0!
#55000
b100 6
1!
#55500
0!
#56000
b100 6
1!
#56500
0!
#57000
b100 6
1!
#57500
0!
#58000
b100 6
1!
#58500
0!
#59000
b100 6
1!
