src/controllers/inst_control.v
// ===========================================
// Instruction Memory Controller Module
// 
// Memory controller to handle requests from the fetcher 
// of the different compute units
//
// VERSION 2
// ===========================================
module inst_controller #(
  parameter NUM_MEM_CHAN = 1,
            NUM_CORES = 4,
            MEM_ADDR_WIDTH = 8,
            MEM_DATA_WIDTH = 16
) (
  input clk,
  input reset,

  // I/O from internal GPU Fetcher blocks 
  output fetch_req_rdy [NUM_CORES-1:0], 
  input fetch_req_val [NUM_CORES-1:0], 
  input [MEM_ADDR_WIDTH-1:0] fetch_req_addr [NUM_CORES-1:0],

  input fetch_resp_rdy [NUM_CORES-1:0], 
  output fetch_resp_val [NUM_CORES-1:0],
  output [MEM_DATA_WIDTH-1:0] fetch_resp_inst [NUM_CORES-1:0],

  // I/O to interface with global memory
  input mem2fetch_req_rdy,
  output mem2fetch_req_val,
  output [MEM_ADDR_WIDTH-1:0] mem2fetch_req_addr, // Uses current pc

  output mem2fetch_resp_rdy, 
  input mem2fetch_resp_val,
  input [MEM_DATA_WIDTH-1:0] mem2fetch_resp_inst,

  // Functional I/O
  input [3:0] compute_state [NUM_CORES-1:0],

  // For debugging
  output [NUM_CORES-1:0] compute_unit
);

localparam  FETCH = 4'd1,
            DECODE = 4'd2;

// Progression localparam
localparam  IDLE = 2'd0,      // Channel is waiting for a memory request
            REQUEST = 2'd1,   // Channel is processing the mem req
            RESPONSE = 2'd2;  // Channel is sending mem resp to appropriate compute unit

reg [1:0] channel_state;
reg [NUM_CORES-1:0] selected_unit;
assign compute_unit = selected_unit;

// Registering outputs 
reg fetch_req_rdy_reg [NUM_CORES-1:0];
reg fetch_resp_val_reg [NUM_CORES-1:0];
reg [MEM_DATA_WIDTH-1:0] fetch_resp_inst_reg [NUM_CORES-1:0];
reg mem2fetch_req_val_reg;
reg [MEM_ADDR_WIDTH-1:0] mem2fetch_req_addr_reg;
reg mem2fetch_resp_rdy_reg;

genvar k;
for (k=0;k<NUM_CORES;k=k+1) begin 
  // assign fetch_req_rdy[i] = fetch_req_rdy_reg[i];
  assign fetch_req_rdy[k] = mem2fetch_req_rdy;
  assign fetch_resp_val[k] = fetch_resp_val_reg[k];
  assign fetch_resp_inst[k] = fetch_resp_inst_reg[k];
end

assign mem2fetch_req_val = mem2fetch_req_val_reg;
assign mem2fetch_req_addr = mem2fetch_req_addr_reg;
assign mem2fetch_resp_rdy = mem2fetch_resp_rdy_reg;

integer i;
always @(posedge clk) begin 
  if (reset) begin 
    for (i=0;i<NUM_CORES;i=i+1) begin 
      fetch_resp_val_reg[i] <= 0;
      fetch_resp_inst_reg[i] <= 0;
    end
    mem2fetch_req_val_reg <= 0;
    mem2fetch_req_addr_reg <= 0;
    mem2fetch_resp_rdy_reg <= 0;
    channel_state <= IDLE;
    selected_unit <= 0;
  end else begin 
    case (channel_state)
      IDLE: begin 
        // Iterate through all compute units to select one to process
        for (i=0;i<NUM_CORES;i=i+1)begin 
          if (fetch_req_val[i]) begin 
            // unit[i] has an active request
            selected_unit <= i;
            channel_state <= REQUEST;
            i = NUM_CORES-1;
          end
        end
      end
      REQUEST: begin 
        mem2fetch_req_val_reg <= fetch_req_val[selected_unit]; 
        mem2fetch_req_addr_reg <= fetch_req_addr[selected_unit];
        mem2fetch_resp_rdy_reg <= fetch_resp_rdy[selected_unit];
        if (mem2fetch_resp_val && fetch_resp_rdy[selected_unit]) begin 
          fetch_resp_val_reg[selected_unit] <= 1;
          fetch_resp_inst_reg[selected_unit] <= mem2fetch_resp_inst;
          channel_state <= RESPONSE;
        end
      end
      RESPONSE: begin 
        if (compute_state[selected_unit] == DECODE) begin 
          // The compute unit finished processing the fetch, reset all connections
          mem2fetch_req_val_reg <= 0; 
          mem2fetch_req_addr_reg <= 0;
          mem2fetch_resp_rdy_reg <= 0;
          fetch_resp_val_reg[selected_unit] <= 0;
          fetch_resp_inst_reg[selected_unit] <= 0;
          selected_unit <= 0;
          channel_state <= IDLE;
        end
      end
    endcase
  end
end

// For debugging
wire [3:0] state_0;
wire [3:0] state_1;
wire [3:0] state_2;
wire [3:0] state_3;
assign state_0 = compute_state[0];
assign state_1 = compute_state[1];
assign state_2 = compute_state[2];
assign state_3 = compute_state[3];
wire fetch_req_val0;
wire fetch_req_val1;
wire fetch_req_val2;
wire fetch_req_val3;
assign fetch_req_val0 = fetch_req_val[0];
assign fetch_req_val1 = fetch_req_val[1];
assign fetch_req_val2 = fetch_req_val[2];
assign fetch_req_val3 = fetch_req_val[3];

endmodule

wrapper/controller/wrapper_instcont.v
`include "../../src/controllers/inst_control.v"
module wrapper_instcont #(
  parameter NUM_MEM_CHAN = 1,
            NUM_CORES = 4,
            MEM_ADDR_WIDTH = 8,
            MEM_DATA_WIDTH = 16
) (
  input clk,
  input reset,

  // I/O from internal GPU Fetcher blocks 
  output fetch_req_rdy [NUM_CORES-1:0], 
  input fetch_req_val [NUM_CORES-1:0], 
  input [MEM_ADDR_WIDTH-1:0] fetch_req_addr [NUM_CORES-1:0],

  input fetch_resp_rdy [NUM_CORES-1:0], 
  output fetch_resp_val [NUM_CORES-1:0],
  output [MEM_DATA_WIDTH-1:0] fetch_resp_inst [NUM_CORES-1:0],

  // I/O to interface with global memory
  input mem2fetch_req_rdy,
  output mem2fetch_req_val,
  output [MEM_ADDR_WIDTH-1:0] mem2fetch_req_addr, // Uses current pc

  output mem2fetch_resp_rdy, 
  input mem2fetch_resp_val,
  input [MEM_DATA_WIDTH-1:0] mem2fetch_resp_inst,

  input [3:0] compute_state [NUM_CORES-1:0],

  output [NUM_CORES-1:0] compute_unit
);

inst_controller #(
  .NUM_MEM_CHAN(NUM_MEM_CHAN),
  .NUM_CORES(NUM_CORES),
  .MEM_ADDR_WIDTH(MEM_ADDR_WIDTH),
  .MEM_DATA_WIDTH(MEM_DATA_WIDTH)
) instructions (
  .clk(clk),
  .reset(reset),
  .fetch_req_rdy(fetch_req_rdy),
  .fetch_req_val(fetch_req_val),
  .fetch_req_addr(fetch_req_addr),
  .fetch_resp_rdy(fetch_resp_rdy),
  .fetch_resp_val(fetch_resp_val),
  .fetch_resp_inst(fetch_resp_inst),
  .mem2fetch_req_rdy(mem2fetch_req_rdy),
  .mem2fetch_req_val(mem2fetch_req_val),
  .mem2fetch_req_addr(mem2fetch_req_addr),
  .mem2fetch_resp_rdy(mem2fetch_resp_rdy),
  .mem2fetch_resp_val(mem2fetch_resp_val),
  .mem2fetch_resp_inst(mem2fetch_resp_inst),
  .compute_state(compute_state),
  .compute_unit(compute_unit)
);

// Dumping
initial begin 
  $dumpfile("instcont_dump.vcd");
  $dumpvars(0, instructions);
end

endmodule

test/instcontrol_test/instcont_dump.vcd
$date
	Sun Jan 12 21:39:55 2025
$end
$version
	Icarus Verilog
$end
$timescale
	1ps
$end
$scope module wrapper_instcont $end
$scope module instructions $end
$var wire 1 ! clk $end
$var wire 4 " compute_unit [3:0] $end
$var wire 1 # fetch_req_val0 $end
$var wire 1 $ fetch_req_val1 $end
$var wire 1 % fetch_req_val2 $end
$var wire 1 & fetch_req_val3 $end
$var wire 8 ' mem2fetch_req_addr [7:0] $end
$var wire 1 ( mem2fetch_req_rdy $end
$var wire 1 ) mem2fetch_req_val $end
$var wire 16 * mem2fetch_resp_inst [15:0] $end
$var wire 1 + mem2fetch_resp_rdy $end
$var wire 1 , mem2fetch_resp_val $end
$var wire 1 - reset $end
$var wire 4 . state_0 [3:0] $end
$var wire 4 / state_1 [3:0] $end
$var wire 4 0 state_2 [3:0] $end
$var wire 4 1 state_3 [3:0] $end
$var parameter 4 2 DECODE $end
$var parameter 4 3 FETCH $end
$var parameter 2 4 IDLE $end
$var parameter 32 5 MEM_ADDR_WIDTH $end
$var parameter 32 6 MEM_DATA_WIDTH $end
$var parameter 32 7 NUM_CORES $end
$var parameter 32 8 NUM_MEM_CHAN $end
$var parameter 2 9 REQUEST $end
$var parameter 2 : RESPONSE $end
$var reg 2 ; channel_state [1:0] $end
$var reg 8 < mem2fetch_req_addr_reg [7:0] $end
$var reg 1 = mem2fetch_req_val_reg $end
$var reg 1 > mem2fetch_resp_rdy_reg $end
$var reg 4 ? selected_unit [3:0] $end
$var integer 32 @ i [31:0] $end
$scope begin genblk1[0] $end
$var parameter 2 A k $end
$upscope $end
$scope begin genblk1[1] $end
$var parameter 2 B k $end
$upscope $end
$scope begin genblk1[2] $end
$var parameter 3 C k $end
$upscope $end
$scope begin genblk1[3] $end
$var parameter 3 D k $end
$upscope $end
$upscope $end
$upscope $end
$enddefinitions $end
$comment Show the parameter values. $end
$dumpall
b11 D
b10 C
b1 B
b0 A
b10 :
b1 9
b1 8
b100 7
b10000 6
b1000 5
b0 4
b1 3
b10 2
$end
#0
$dumpvars
bx @
bx ?
x>
x=
bx <
bx ;
bz 1
bz 0
bz /
bz .
0-
z,
x+
bz *
x)
z(
bx '
z&
z%
z$
z#
bx "
1!
$end
#500
0!
#1000
b0 "
b0 ?
b0 ;
0+
0>
b0 '
b0 <
0)
0=
b100 @
1!
1-
#1500
0!
#2000
b100 @
1!
0-
#2500
0!
#3000
b100 @
1!
#3500
0!
#4000
b100 @
1!
#4500
0!
#5000
b100 @
1!
#5500
0!
#6000
b100 @
1!
#6500
0!
#7000
b100 @
1!
#7500
0!
#8000
b100 @
1!
#8500
0!
#9000
b100 @
1!
#9500
0!
#10000
b100 @
1!
b1 .
b1 /
b1 0
b1 1
1#
1$
1%
1&
b0 *
0,
1(
#10500
0!
#11000
b1 ;
b100 @
1!
#11500
0!
#12000
1+
1>
b1000 '
b1000 <
1)
1=
1!
#12500
0!
#13000
b1100010010 *
1,
0(
1!
#13500
0!
#14000
b10 ;
1!
#14500
0!
#15000
b10 .
0#
1!
#15500
0!
#16000
b0 ;
0+
0>
b0 '
b0 <
0)
0=
1!
#16500
0!
#17000
b0 *
0,
1(
b1 ;
b1 "
b1 ?
b100 @
1!
#17500
0!
#18000
b110 '
b110 <
1)
1=
1!
#18500
0!
#19000
1+
1>
1!
#19500
0!
#20000
b1001000000101001 *
1,
0(
1!
#20500
0!
#21000
b10 ;
1!
#21500
0!
#22000
b10 /
0$
1!
#22500
0!
#23000
b0 ;
b0 "
b0 ?
0+
0>
b0 '
b0 <
0)
0=
1!
#23500
0!
#24000
b0 *
0,
1(
b1 ;
b10 "
b10 ?
b100 @
1!
#24500
0!
#25000
b100 '
b100 <
1)
1=
1!
#25500
0!
#26000
1+
1>
1!
#26500
0!
#27000
b100110101111 *
1,
0(
1!
#27500
0!
#28000
b10 ;
1!
#28500
0!
#29000
b10 0
0%
1!
#29500
0!
#30000
b0 ;
b0 "
b0 ?
0+
0>
b0 '
b0 <
0)
0=
1!
#30500
0!
#31000
b0 *
0,
1(
b1 ;
b11 "
b11 ?
b100 @
1!
#31500
0!
#32000
b10 '
b10 <
1)
1=
1!
#32500
0!
#33000
1+
1>
1!
#33500
0!
#34000
b1000101000000100 *
1,
0(
1!
#34500
0!
#35000
b10 ;
1!
#35500
0!
#36000
b10 1
0&
1!
#36500
0!
#37000
b0 ;
b0 "
b0 ?
0+
0>
b0 '
b0 <
0)
0=
1!
#37500
0!
#38000
b0 *
0,
1(
b100 @
1!
#38500
0!
#39000
b100 @
1!
#39500
0!
#40000
b100 @
1!
#40500
0!
#41000
b100 @
1!
#41500
0!
#42000
b100 @
1!
#42500
0!
#43000
b100 @
1!
#43500
0!
#44000
b100 @
1!
#44500
0!
#45000
b100 @
1!
#45500
0!
#46000
b100 @
1!
#46500
0!
#47000
b100 @
1!
#47500
0!
#48000
b100 @
1!
#48500
0!
#49000
b100 @
1!
#49500
0!
#50000
b100 @
1!
#50500
0!
#51000
b100 @
1!
#51500
0!
#52000
b100 @
1!
#52500
0!
#53000
b100 @
1!
#53500
0!
#54000
b100 @
1!
#54500
0!
#55000
b100 @
1!
#55500
0!
#56000
b100 @
1!
#56500
0!
#57000
b100 @
1!
#57500
0!
#58000
b100 @
1!
#58500
0!
#59000
b100 @
1!
#59500
0!
#60000
b100 @
1!
#60500
0!
#61000
b100 @
1!
#61500
0!
#62000
b100 @
1!
#62500
0!
#63000
b100 @
1!
#63500
0!
#64000
b100 @
1!
#64500
0!
#65000
b100 @
1!
#65500
0!
#66000
b100 @
1!
#66500
0!
#67000
b100 @
1!
#67500
0!
#68000
b100 @
1!
#68500
0!
#69000
b100 @
1!
#69500
0!
#70000
b100 @
1!
#70500
0!
#71000
b100 @
1!
#71500
0!
#72000
b100 @
1!
#72500
0!
#73000
b100 @
1!
#73500
0!
#74000
b100 @
1!
#74500
0!
#75000
b100 @
1!
#75500
0!
#76000
b100 @
1!
#76500
0!
#77000
b100 @
1!
#77500
0!
#78000
b100 @
1!
#78500
0!
#79000
b100 @
1!
#79500
0!
#80000
b100 @
1!
#80500
0!
#81000
b100 @
1!
#81500
0!
#82000
b100 @
1!
#82500
0!
#83000
b100 @
1!
#83500
0!
#84000
b100 @
1!
#84500
0!
#85000
b100 @
1!
#85500
0!
#86000
b100 @
1!
#86500
0!
#87000
b100 @
1!
#87500
0!
#88000
b100 @
1!
#88500
0!
#89000
b100 @
1!
#89500
0!
#90000
b100 @
1!
#90500
0!
#91000
b100 @
1!
#91500
0!
#92000
b100 @
1!
#92500
0!
#93000
b100 @
1!
#93500
0!
#94000
b100 @
1!
#94500
0!
#95000
b100 @
1!
#95500
0!
#96000
b100 @
1!
#96500
0!
#97000
b100 @
1!
#97500
0!
#98000
b100 @
1!
#98500
0!
#99000
b100 @
1!
#99500
0!
#100000
b100 @
1!
#100500
0!
#101000
b100 @
1!
#101500
0!
#102000
b100 @
1!
#102500
0!
#103000
b100 @
1!
#103500
0!
#104000
b100 @
1!
#104500
0!
#105000
b100 @
1!
#105500
0!
#106000
b100 @
1!
#106500
0!
#107000
b100 @
1!
#107500
0!
#108000
b100 @
1!
#108500
0!
#109000
b100 @
1!
